Workbook

Sheet Key Numbers
A1: Rubin USDF Model 2026 — KEY NUMBERS (reference tab)
A2: All sizing and data-product raw numbers live here; every other tab except Cost Inputs is calculated from this tab. Blue = raw input · Black = formula · Yellow = key assumption · Column D = alternate units or how it is derived.
A3: OBSERVING
A4: Observing nights per year | B4: 300 | C4: nights | D4: 330 scheduled less planned/unplanned outages
A5: Visits per night | B5: 700 | C5: visits | D5: 2.1M visits / 10 yr / 300 nights
A6: Image size (logical) | B6: 0.00819222 | C6: TB | D6: 8.19 GB per exposure
A7: Raw compression ratio | B7: 0.464 | C7: ratio | D7: 3.8 GB on wire / 8.19 GB logical
A8: Input data per survey year | B8: =B4*B5*B6*B7 | C8: TB | D8: nights x visits x image size x compression
A10: DRP COMPUTE
A11: DRP core-hours per input TB | B11: 20571 | C11: ch/TB | D11: calibrated: 16.416M core-hrs / 798 TB
A12: DR1 compute (measured basis) | B12: 16416000 | C12: core-hrs | D12: reference; equals 5,700 node-days at 120 cores/node
A13: DP2 compute (actual, on Milano) | B13: 970 | C13: node-days | D13: reference; equals 2.79M core-hours at 120 cores/node
A14: Cores per batch node | B14: 120 | C14: cores | D14: Milano and Torino both 120
A15: DRP processing window | B15: 200 | C15: days | D15: assumed campaign length
A16: Idle / inter-stage multiplier | B16: 1.35 | C16: x | D16: placeholder in suggested 1.3-1.5 range
A17: USDF RSP extra load fraction | B17: 0.01 | C17: fraction | D17: USDF only; partner facilities do not carry this
A18: Developer / pilot batch load | B18: 55 | C18: node-days/yr | D18: observed ~165 node-days over 3 years
A19: Safety margin | B19: 1.5 | C19: x | D19: applied as a separate line, not inside peak-core demand
A21: DRP STORAGE (DR1 basis — see dataset-type breakdown at foot of tab)
A22: DP2 total DRP output (actual) | B22: 7.43 | C22: PB | D22: campaign as run; fitted inside the 30 PB installed
A23: DP2 release products (actual) | B23: 0.32 | C23: PB
A24: DR-era campaign output per survey-yr (BYTES WRITTEN) | B24: =B120 | C24: PB | D24: total written over the campaign; equals the dataset-type table total below
A25: of which release products (RETAINED) | B25: 1.6 | C25: PB | D25: visit_image compressed + standardized catalogs
A26: of which intermediates (TRANSIENT) | B26: =B24-B25 | C26: PB | D26: warps, templates, predetection images, footprints
A27: Live-intermediate fraction (HIGH WATERMARK) | B27: 0.35 | C27: fraction | D27: UNMEASURED. Fraction of intermediates resident at once; dominates the disk budget
A28: Release retention window | B28: 3 | C28: releases | D28: how many data releases stay on floor
A29: Raw + calibration per survey year | B29: 1117 | C29: TB | D29: science + calibration + engineering frames, compressed
A30: Prompt Tier-1 per year | B30: 1680 | C30: TB | D30: 5.6 TB/night x 300 nights, long-term retention
A31: Prompt Tier-2 (rolling) | B31: 180 | C31: TB | D31: 6.0 TB/night x 30-day window
A32: Other on-floor allowance | B32: 0.2 | C32: fraction | D32: user areas, APDB, sims, misc — applied to the on-floor total
A34: TAPE / ARCHIVE (cumulative — archived data is never deleted)
A35: Raw + calibration copies held on USDF tape | B35: 1 | C35: copies | D35: further copies of raw data are held at partner facilities, not costed here
A36: Release products archived to tape | B36: 1 | C36: fraction of releases | D36: 1.0 = every data release is preserved permanently
A37: On-floor data backed up to tape | B37: 0 | C37: fraction of on-floor | D37: 0 = no NEW backup modelled; a separate backup system already exists, see the row below
A38: Archive already on the floor (HPSS) | B38: 8200 | C38: TB | D38: UNVERIFIED: only a fraction of this could be independently attested
A39: TSM backup already on the floor | B39: 10800 | C39: TB | D39: reference only: not projected forward
A40: Tape capacity assumed available to Rubin | B40: 66300 | C40: TB | D40: UNVERIFIED. From a hedged reading of a shared-facility accounting system; the facility is multi-tenant and library slots / drive bandwidth are shared. Set to 0 for the no-headroom case
A42: ALERT PRODUCTION / PROMPT (USDF only — partner facilities do not run AP)
A43: Alert Production cores | B43: 1188 | C43: cores | D43: runs nightly on Kubernetes, not on the batch fleet
A44: Alerts per visit | B44: 10000 | C44: alerts | D44: about 7M alerts per night at 700 visits
A45: Cores per K8s node | B45: 48 | C45: cores | D45: planner figure; the hardware is 32c/64HT — reconciliation pending
A47: USER / RSP / DAC COMPUTE (USDF only)
A48: DAC / LSP cores as fraction of DRP | B48: 0.1 | C48: fraction | D48: the standing user-compute allowance, as a fraction of DRP
A49: Staff cores as fraction of DAC | B49: 0.1 | C49: fraction
A51: APDB / CASSANDRA
A52: APDB reference size | B52: 4.5 | C52: TB | D52: measured at the reference visit count below
A53: APDB reference visits | B53: 57000 | C53: visits | D53: APDB scales with cumulative visits
A54: Cassandra nodes deployed | B54: 12 | C54: nodes
A55: APDB off-site backup at end of survey | B55: 100 | C55: TB | D55: order-of-magnitude projection; about 0.5 TB today
A57: USDF FLEET (2026)
A58: Batch nodes | B58: =B60+B61 | C58: nodes | D58: 110 Milano + 35 Torino
A59: Batch cores (raw) | B59: =B58*B14 | C59: cores | D59: raw core count, ignores per-core speed
A60: Milano nodes | B60: 110 | C60: nodes
A61: Torino nodes | B61: 35 | C61: nodes
A62: Torino per-core speedup vs Milano | B62: 2 | C62: x | D62: measured across DP2-era tasks; higher clock and memory bandwidth
A63: Fleet capacity, Milano-equivalent cores | B63: =(B60+B61*B62)*B14 | C63: cores | D63: demand is Milano-calibrated, so capacity is expressed the same way
A64: Installed storage | B64: 30 | C64: PB
A65: K8s nodes deployed | B65: 75 | C65: nodes
A66: Interactive nodes | B66: 11 | C66: nodes | D66: shared bare-metal login / analysis nodes
A67: Cores per interactive node | B67: 64 | C67: cores
A69: FACILITY SPLIT (DRP COMPUTE)
A70: France / CC-IN2P3 share | B70: 0.4 | C70: % | D70: long-run aggregate
A71: UK / UKDF share (10-yr aggregate) | B71: 0.25 | C71: % | D71: front-loaded ~40% of year 1, tapering to this aggregate
A72: USDF share (residual, aggregate) | B72: =1-B70-B71 | C72: %
A73: UK provisioned capacity | B73: 40000000 | C73: ch/yr | D73: shared infrastructure: ~9k cores for six months
A75: QSERV (catalog database)
A76: Qserv nodes deployed | B76: 92 | C76: nodes | D76: hardware specification is documented on the Qserv tab
A77: Qserv replication factor | B77: 3 | C77: x | D77: planning value. Every on-disk catalogue figure scales linearly with it; at 2 they fall by a third
A78: Overlap uplift on chunk bytes | B78: 0.237 | C78: fraction | D78: overlap regions are extra tables holding neighbouring rows. Applied to the modelled columns only; the measured column already contains its own. Observed range across catalogues 6% to 24%, driven by how much of a catalogue is director tables
A79: Qserv retention window | B79: 3 | C79: releases | D79: sliding window of releases held in the database
A80: Object row size | B80: 1896 | C80: bytes
A81: Object extra row size | B81: 21005 | C81: bytes | D81: uncompressed logical size of the auxiliary per-object tables; the largest single term in the catalogue total
A82: Source row size | B82: 467 | C82: bytes
A83: Forced-source row size | B83: 41 | C83: bytes | D83: held flat: the forced-source schema is fixed, so it is the one row size that does not widen between releases
A84: Row-size growth per release | B84: 0.03 | C84: fraction | D84: schemas widen as measured columns are added. Compounds per RELEASE, so it is sensitive to release cadence rather than to elapsed years. Applied to the object and source row sizes above, not to forced sources
A85: LDM row size to stored-bytes factor | B85: 1 | C85: ratio | D85: UNANCHORED. Maps the logical row sizes above onto what Qserv stores before filesystem compression. Set to 1.0 as the neutral assumption: filesystem compression is already carried in the per-node capacity, so applying it here as well would count it twice. At DR1, 1.0 gives about 1,450 TB per copy and 0.32 about 460 TB
A86: Independent DR1 catalogue estimate, low | B86: 2 | C86: PB | D86: one copy, before replication. Used as a calibration band on the Qserv tab; drives no downstream figure
A87: Independent DR1 catalogue estimate, high | B87: 3 | C87: PB | D87: one copy, before replication
A88: Measured data-preview catalogue (logical) | B88: 33.45 | C88: TB | D88: unique-chunk total, before replication. Anchors the data-preview column on measurement instead of modelling it. The on-disk preview figure is this times the planning replication factor, so it is a provisioning figure, not a measurement
A89: Measured data-preview indexes (logical) | B89: 3.24 | C89: TB | D89: index portion of the row above; already included in it
A91: DP2 / EDP2 REFERENCE (not used in projections)
A92: DP2 visits processed | B92: 30000 | C92: visits | D92: one survey-year is ~210,000 visits
A93: EDP2 distributed subset (total) | B93: 59.15 | C93: TB | D93: EDP2 is an early subset of DP2, not full DP2
A94: EDP2 deep_coadd | B94: 28 | C94: TB | D94: 925,460 files
A95: EDP2 object_scarlet_models | B95: 11 | C95: TB | D95: product not yet in the model
A96: HiPS single-band maps | B96: 18 | C96: TB | D96: small-file heavy; see file count below
A97: HiPS file count | B97: 36 | C97: millions | D97: capacity is small but the object count stresses filesystem metadata
A99: DR1 DATASET-TYPE BREAKDOWN — source of BYTES WRITTEN and the file count
A100: Dataset type (DR1, compressed) | B100: PB | C100: files | D100: largest dataset types by size; the remainder are carried in the row below
A101: direct_warp | B101: 7.437 | C101: 107391908
A102: direct_warp_noise0 | B102: 7.42 | C102: 107391908
A103: psf_matched_warp | B103: 5.382 | C103: 107391908
A104: template_detector | B104: 5.311 | C104: 37270840
A105: difference_image_predetection | B105: 4.049 | C105: 37270840
A106: template_matched | B106: 3.902 | C106: 37270840
A107: difference_image | B107: 3.873 | C107: 37270840
A108: post_isr_image | B108: 3.341 | C108: 35596260
A109: deep_coadd_cell_predetection | B109: 1.534 | C109: 7398852
A110: visit_image (RELEASE) | B110: 1.083 | C110: 37270840
A111: preliminary_visit_image | B111: 1.04 | C111: 35596260
...

Sheet All at USDF
A1: Scenario A — Everything runs at USDF (100% of DRP). All cells calculated from Key Numbers.
A2: Metric | B2: Unit | C2: LOY1 | D2: LOY2 | E2: LOY3 | F2: LOY4 | G2: LOY5 | H2: LOY6 | I2: LOY7 | J2: LOY8 | K2: LOY9 | L2: LOY10
A3: Fiscal Year | C3: FY2026 | D3: FY2027 | E3: FY2028 | F3: FY2029 | G3: FY2030 | H3: FY2031 | I3: FY2032 | J3: FY2033 | K3: FY2034 | L3: FY2035
A4: Milestone | C4: DP2 (actual) | D4: DR1 | E4: DR2 | F4: DR3 | G4: DR4 | H4: DR5 | I4: DR6 | J4: DR7 | K4: DR8 | L4: DR9
A6: DRP COMPUTE — core-hours / node-days / peak cores (LOY1 = DP2 actuals)
A7: Survey years of input processed | B7: years | C7: ='Key Numbers'!$B$92/('Key Numbers'!$B$4*'Key Numbers'!$B$5) | D7: 1 | E7: 2 | F7: 3 | G7: 4 | H7: 5 | I7: 6 | J7: 7 | K7: 8 | L7: 9
A8: Cumulative input data | B8: TB | C8: =C7*'Key Numbers'!$B$8 | D8: =D7*'Key Numbers'!$B$8 | E8: =E7*'Key Numbers'!$B$8 | F8: =F7*'Key Numbers'!$B$8 | G8: =G7*'Key Numbers'!$B$8 | H8: =H7*'Key Numbers'!$B$8 | I8: =I7*'Key Numbers'!$B$8 | J8: =J7*'Key Numbers'!$B$8 | ... L8: =L7*'Key Numbers'!$B$8
A9: DRP work — core-hours | B9: core-hrs | C9: ='Key Numbers'!$B$13*'Key Numbers'!$B$14*24 | D9: =D8*'Key Numbers'!$B$11+D7*'Key Numbers'!$B$18*'Key Numbers'!$B$14*24 | E9: =E8*'Key Numbers'!$B$11+E7*'Key Numbers'!$B$18*'Key Numbers'!$B$14*24 | F9: =F8*'Key Numbers'!$B$11+F7*'Key Numbers'!$B$18*'Key Numbers'!$B$14*24 | G9: =G8*'Key Numbers'!$B$11+G7*'Key Numbers'!$B$18*'Key Numbers'!$B$14*24 | H9: =H8*'Key Numbers'!$B$11+H7*'Key Numbers'!$B$18*'Key Numbers'!$B$14*24 | I9: =I8*'Key Numbers'!$B$11+I7*'Key Numbers'!$B$18*'Key Numbers'!$B$14*24 | J9: =J8*'Key Numbers'!$B$11+J7*'Key Numbers'!$B$18*'Key Numbers'!$B$14*24 | K9: =K8*'Key Numbers'!$B$11+K7*'Key Numbers'!$B$18*'Key Numbers'!$B$14*24 | L9: =L8*'Key Numbers'!$B$11+L7*'Key Numbers'!$B$18*'Key Numbers'!$B$14*24
A10: DRP work — node-days (at 120 cores/node) | B10: node-days | C10: =C9/(24*'Key Numbers'!$B$14) | D10: =D9/(24*'Key Numbers'!$B$14) | E10: =E9/(24*'Key Numbers'!$B$14) | F10: =F9/(24*'Key Numbers'!$B$14) | G10: =G9/(24*'Key Numbers'!$B$14) | H10: =H9/(24*'Key Numbers'!$B$14) | I10: =I9/(24*'Key Numbers'!$B$14) | J10: =J9/(24*'Key Numbers'!$B$14) | ... L10: =L9/(24*'Key Numbers'!$B$14)
A11: DRP work — peak concurrent cores (in window) | B11: cores | C11: =ROUND(C9/('Key Numbers'!$B$15*24)*'Key Numbers'!$B$16*(1+'Key Numbers'!$B$17),0) | D11: =ROUND(D9/('Key Numbers'!$B$15*24)*'Key Numbers'!$B$16*(1+'Key Numbers'!$B$17),0) | E11: =ROUND(E9/('Key Numbers'!$B$15*24)*'Key Numbers'!$B$16*(1+'Key Numbers'!$B$17),0) | F11: =ROUND(F9/('Key Numbers'!$B$15*24)*'Key Numbers'!$B$16*(1+'Key Numbers'!$B$17),0) | G11: =ROUND(G9/('Key Numbers'!$B$15*24)*'Key Numbers'!$B$16*(1+'Key Numbers'!$B$17),0) | H11: =ROUND(H9/('Key Numbers'!$B$15*24)*'Key Numbers'!$B$16*(1+'Key Numbers'!$B$17),0) | I11: =ROUND(I9/('Key Numbers'!$B$15*24)*'Key Numbers'!$B$16*(1+'Key Numbers'!$B$17),0) | J11: =ROUND(J9/('Key Numbers'!$B$15*24)*'Key Numbers'!$B$16*(1+'Key Numbers'!$B$17),0) | ... L11: =ROUND(L9/('Key Numbers'!$B$15*24)*'Key Numbers'!$B$16*(1+'Key Numbers'!$B$17),0)
A12: Core-hours with safety margin | B12: core-hrs | C12: =C9*'Key Numbers'!$B$19 | D12: =D9*'Key Numbers'!$B$19 | E12: =E9*'Key Numbers'!$B$19 | F12: =F9*'Key Numbers'!$B$19 | G12: =G9*'Key Numbers'!$B$19 | H12: =H9*'Key Numbers'!$B$19 | I12: =I9*'Key Numbers'!$B$19 | J12: =J9*'Key Numbers'!$B$19 | ... L12: =L9*'Key Numbers'!$B$19
A13: Batch nodes needed (peak) | B13: nodes | C13: =ROUNDUP(C11/'Key Numbers'!$B$14,0) | D13: =ROUNDUP(D11/'Key Numbers'!$B$14,0) | E13: =ROUNDUP(E11/'Key Numbers'!$B$14,0) | F13: =ROUNDUP(F11/'Key Numbers'!$B$14,0) | G13: =ROUNDUP(G11/'Key Numbers'!$B$14,0) | H13: =ROUNDUP(H11/'Key Numbers'!$B$14,0) | I13: =ROUNDUP(I11/'Key Numbers'!$B$14,0) | J13: =ROUNDUP(J11/'Key Numbers'!$B$14,0) | ... L13: =ROUNDUP(L11/'Key Numbers'!$B$14,0)
A14: USDF fleet, Milano-equivalent cores | B14: cores | C14: ='Key Numbers'!$B$63 | D14: ='Key Numbers'!$B$63 | E14: ='Key Numbers'!$B$63 | F14: ='Key Numbers'!$B$63 | G14: ='Key Numbers'!$B$63 | H14: ='Key Numbers'!$B$63 | I14: ='Key Numbers'!$B$63 | J14: ='Key Numbers'!$B$63 | ... L14: ='Key Numbers'!$B$63
A15: Fleet utilization (peak / Milano-equivalent) | B15: % | C15: =C11/C14 | D15: =D11/D14 | E15: =E11/E14 | F15: =F11/F14 | G15: =G11/G14 | H15: =H11/H14 | I15: =I11/I14 | J15: =J11/J14 | ... L15: =L11/L14
A17: DRP STORAGE — bytes written vs on-floor need (these are different things)
A18: Campaign output this FY — BYTES WRITTEN | B18: PB | C18: ='Key Numbers'!$B$22 | D18: ='Key Numbers'!$B$24*D7 | E18: ='Key Numbers'!$B$24*E7 | F18: ='Key Numbers'!$B$24*F7 | G18: ='Key Numbers'!$B$24*G7 | H18: ='Key Numbers'!$B$24*H7 | I18: ='Key Numbers'!$B$24*I7 | J18: ='Key Numbers'!$B$24*J7 | K18: ='Key Numbers'!$B$24*K7 | L18: ='Key Numbers'!$B$24*L7
A19: same in TB | B19: TB | C19: =C18*1000 | D19: =D18*1000 | E19: =E18*1000 | F19: =F18*1000 | G19: =G18*1000 | H19: =H18*1000 | I19: =I18*1000 | J19: =J18*1000 | ... L19: =L18*1000
A20: of which release products (retained) | B20: PB | C20: ='Key Numbers'!$B$23 | D20: ='Key Numbers'!$B$25*D7 | E20: ='Key Numbers'!$B$25*E7 | F20: ='Key Numbers'!$B$25*F7 | G20: ='Key Numbers'!$B$25*G7 | H20: ='Key Numbers'!$B$25*H7 | I20: ='Key Numbers'!$B$25*I7 | J20: ='Key Numbers'!$B$25*J7 | K20: ='Key Numbers'!$B$25*K7 | L20: ='Key Numbers'!$B$25*L7
A21: of which intermediates (transient) | B21: PB | C21: =C18-C20 | D21: =D18-D20 | E21: =E18-E20 | F21: =F18-F20 | G21: =G18-G20 | H21: =H18-H20 | I21: =I18-I20 | J21: =J18-J20 | ... L21: =L18-L20
A22: On floor: live intermediates (peak) | B22: PB | C22: =C21*'Key Numbers'!$B$27 | D22: =D21*'Key Numbers'!$B$27 | E22: =E21*'Key Numbers'!$B$27 | F22: =F21*'Key Numbers'!$B$27 | G22: =G21*'Key Numbers'!$B$27 | H22: =H21*'Key Numbers'!$B$27 | I22: =I21*'Key Numbers'!$B$27 | J22: =J21*'Key Numbers'!$B$27 | ... L22: =L21*'Key Numbers'!$B$27
A23: On floor: retained releases (sliding window) | B23: PB | C23: ='Key Numbers'!$B$25*(C7*MIN(C7,'Key Numbers'!$B$28)-(MIN(C7,'Key Numbers'!$B$28)-1)*MIN(C7,'Key Numbers'!$B$28)/2) | D23: ='Key Numbers'!$B$25*(D7*MIN(D7,'Key Numbers'!$B$28)-(MIN(D7,'Key Numbers'!$B$28)-1)*MIN(D7,'Key Numbers'!$B$28)/2) | E23: ='Key Numbers'!$B$25*(E7*MIN(E7,'Key Numbers'!$B$28)-(MIN(E7,'Key Numbers'!$B$28)-1)*MIN(E7,'Key Numbers'!$B$28)/2) | F23: ='Key Numbers'!$B$25*(F7*MIN(F7,'Key Numbers'!$B$28)-(MIN(F7,'Key Numbers'!$B$28)-1)*MIN(F7,'Key Numbers'!$B$28)/2) | G23: ='Key Numbers'!$B$25*(G7*MIN(G7,'Key Numbers'!$B$28)-(MIN(G7,'Key Numbers'!$B$28)-1)*MIN(G7,'Key Numbers'!$B$28)/2) | H23: ='Key Numbers'!$B$25*(H7*MIN(H7,'Key Numbers'!$B$28)-(MIN(H7,'Key Numbers'!$B$28)-1)*MIN(H7,'Key Numbers'!$B$28)/2) | I23: ='Key Numbers'!$B$25*(I7*MIN(I7,'Key Numbers'!$B$28)-(MIN(I7,'Key Numbers'!$B$28)-1)*MIN(I7,'Key Numbers'!$B$28)/2) | J23: ='Key Numbers'!$B$25*(J7*MIN(J7,'Key Numbers'!$B$28)-(MIN(J7,'Key Numbers'!$B$28)-1)*MIN(J7,'Key Numbers'!$B$28)/2) | ... L23: ='Key Numbers'!$B$25*(L7*MIN(L7,'Key Numbers'!$B$28)-(MIN(L7,'Key Numbers'!$B$28)-1)*MIN(L7,'Key Numbers'!$B$28)/2)
A24: On floor: raw + calibration, cumulative | B24: PB | C24: ='Key Numbers'!$B$29*(COLUMN()-2)/1000 | D24: ='Key Numbers'!$B$29*(COLUMN()-2)/1000 | E24: ='Key Numbers'!$B$29*(COLUMN()-2)/1000 | F24: ='Key Numbers'!$B$29*(COLUMN()-2)/1000 | G24: ='Key Numbers'!$B$29*(COLUMN()-2)/1000 | H24: ='Key Numbers'!$B$29*(COLUMN()-2)/1000 | I24: ='Key Numbers'!$B$29*(COLUMN()-2)/1000 | J24: ='Key Numbers'!$B$29*(COLUMN()-2)/1000 | ... L24: ='Key Numbers'!$B$29*(COLUMN()-2)/1000
A25: On floor: prompt products (Tier-1 cumulative + Tier-2) | B25: PB | C25: =('Key Numbers'!$B$30*(COLUMN()-2)+'Key Numbers'!$B$31)/1000 | D25: =('Key Numbers'!$B$30*(COLUMN()-2)+'Key Numbers'!$B$31)/1000 | E25: =('Key Numbers'!$B$30*(COLUMN()-2)+'Key Numbers'!$B$31)/1000 | F25: =('Key Numbers'!$B$30*(COLUMN()-2)+'Key Numbers'!$B$31)/1000 | G25: =('Key Numbers'!$B$30*(COLUMN()-2)+'Key Numbers'!$B$31)/1000 | H25: =('Key Numbers'!$B$30*(COLUMN()-2)+'Key Numbers'!$B$31)/1000 | I25: =('Key Numbers'!$B$30*(COLUMN()-2)+'Key Numbers'!$B$31)/1000 | J25: =('Key Numbers'!$B$30*(COLUMN()-2)+'Key Numbers'!$B$31)/1000 | ... L25: =('Key Numbers'!$B$30*(COLUMN()-2)+'Key Numbers'!$B$31)/1000
A26: Subtotal of modelled datasets | B26: PB | C26: =SUM(C22:C25) | D26: =SUM(D22:D25) | E26: =SUM(E22:E25) | F26: =SUM(F22:F25) | G26: =SUM(G22:G25) | H26: =SUM(H22:H25) | I26: =SUM(I22:I25) | J26: =SUM(J22:J25) | ... L26: =SUM(L22:L25)
A27: Other / misc allowance (user areas, APDB, sims) | B27: PB | C27: =C26*'Key Numbers'!$B$32 | D27: =D26*'Key Numbers'!$B$32 | E27: =E26*'Key Numbers'!$B$32 | F27: =F26*'Key Numbers'!$B$32 | G27: =G26*'Key Numbers'!$B$32 | H27: =H26*'Key Numbers'!$B$32 | I27: =I26*'Key Numbers'!$B$32 | J27: =J26*'Key Numbers'!$B$32 | ... L27: =L26*'Key Numbers'!$B$32
A28: ON-FLOOR DISK NEED (drives purchases) | B28: PB | C28: =C26+C27 | D28: =D26+D27 | E28: =E26+E27 | F28: =F26+F27 | G28: =G26+G27 | H28: =H26+H27 | I28: =I26+I27 | J28: =J26+J27 | ... L28: =L26+L27
A29: same in TB | B29: TB | C29: =C28*1000 | D29: =D28*1000 | E29: =E28*1000 | F29: =F28*1000 | G29: =G28*1000 | H29: =H28*1000 | I29: =I28*1000 | J29: =J28*1000 | ... L29: =L28*1000
A30: Installed storage today | B30: PB | C30: ='Key Numbers'!$B$64 | D30: ='Key Numbers'!$B$64 | E30: ='Key Numbers'!$B$64 | F30: ='Key Numbers'!$B$64 | G30: ='Key Numbers'!$B$64 | H30: ='Key Numbers'!$B$64 | I30: ='Key Numbers'!$B$64 | J30: ='Key Numbers'!$B$64 | ... L30: ='Key Numbers'!$B$64
A32: TAPE / ARCHIVE — cumulative footprint (archived data is never deleted)
A33: Raw + calibration archived, cumulative | B33: PB | C33: ='Key Numbers'!$B$29*'Key Numbers'!$B$35*(COLUMN()-2)/1000 | D33: ='Key Numbers'!$B$29*'Key Numbers'!$B$35*(COLUMN()-2)/1000 | E33: ='Key Numbers'!$B$29*'Key Numbers'!$B$35*(COLUMN()-2)/1000 | F33: ='Key Numbers'!$B$29*'Key Numbers'!$B$35*(COLUMN()-2)/1000 | G33: ='Key Numbers'!$B$29*'Key Numbers'!$B$35*(COLUMN()-2)/1000 | H33: ='Key Numbers'!$B$29*'Key Numbers'!$B$35*(COLUMN()-2)/1000 | I33: ='Key Numbers'!$B$29*'Key Numbers'!$B$35*(COLUMN()-2)/1000 | J33: ='Key Numbers'!$B$29*'Key Numbers'!$B$35*(COLUMN()-2)/1000 | ... L33: ='Key Numbers'!$B$29*'Key Numbers'!$B$35*(COLUMN()-2)/1000
A34: Release products archived, cumulative | B34: PB | C34: ='Key Numbers'!$B$23*'Key Numbers'!$B$36 | D34: ='Key Numbers'!$B$25*D7*(D7+1)/2*'Key Numbers'!$B$36 | E34: ='Key Numbers'!$B$25*E7*(E7+1)/2*'Key Numbers'!$B$36 | F34: ='Key Numbers'!$B$25*F7*(F7+1)/2*'Key Numbers'!$B$36 | G34: ='Key Numbers'!$B$25*G7*(G7+1)/2*'Key Numbers'!$B$36 | H34: ='Key Numbers'!$B$25*H7*(H7+1)/2*'Key Numbers'!$B$36 | I34: ='Key Numbers'!$B$25*I7*(I7+1)/2*'Key Numbers'!$B$36 | J34: ='Key Numbers'!$B$25*J7*(J7+1)/2*'Key Numbers'!$B$36 | K34: ='Key Numbers'!$B$25*K7*(K7+1)/2*'Key Numbers'!$B$36 | L34: ='Key Numbers'!$B$25*L7*(L7+1)/2*'Key Numbers'!$B$36
A35: Backup of on-floor data | B35: PB | C35: =C28*'Key Numbers'!$B$37 | D35: =D28*'Key Numbers'!$B$37 | E35: =E28*'Key Numbers'!$B$37 | F35: =F28*'Key Numbers'!$B$37 | G35: =G28*'Key Numbers'!$B$37 | H35: =H28*'Key Numbers'!$B$37 | I35: =I28*'Key Numbers'!$B$37 | J35: =J28*'Key Numbers'!$B$37 | ... L35: =L28*'Key Numbers'!$B$37
A36: TAPE FOOTPRINT, cumulative (incl. archive already on floor) | B36: PB | C36: =SUM(C33:C35)+'Key Numbers'!$B$38/1000 | D36: =SUM(D33:D35)+'Key Numbers'!$B$38/1000 | E36: =SUM(E33:E35)+'Key Numbers'!$B$38/1000 | F36: =SUM(F33:F35)+'Key Numbers'!$B$38/1000 | G36: =SUM(G33:G35)+'Key Numbers'!$B$38/1000 | H36: =SUM(H33:H35)+'Key Numbers'!$B$38/1000 | I36: =SUM(I33:I35)+'Key Numbers'!$B$38/1000 | J36: =SUM(J33:J35)+'Key Numbers'!$B$38/1000 | ... L36: =SUM(L33:L35)+'Key Numbers'!$B$38/1000
A37: same in TB | B37: TB | C37: =C36*1000 | D37: =D36*1000 | E37: =E36*1000 | F37: =F36*1000 | G37: =G36*1000 | H37: =H36*1000 | I37: =I36*1000 | J37: =J36*1000 | ... L37: =L36*1000
A38: Tape capacity assumed available (UNVERIFIED) | B38: TB | C38: ='Key Numbers'!$B$40 | D38: ='Key Numbers'!$B$40 | E38: ='Key Numbers'!$B$40 | F38: ='Key Numbers'!$B$40 | G38: ='Key Numbers'!$B$40 | H38: ='Key Numbers'!$B$40 | I38: ='Key Numbers'!$B$40 | J38: ='Key Numbers'!$B$40 | ... L38: ='Key Numbers'!$B$40
A39: Cumulative tape capacity to buy | B39: TB | C39: =MAX(0,C37-C38) | D39: =MAX(0,D37-D38) | E39: =MAX(0,E37-E38) | F39: =MAX(0,F37-F38) | G39: =MAX(0,G37-G38) | H39: =MAX(0,H37-H38) | I39: =MAX(0,I37-I38) | J39: =MAX(0,J37-J38) | ... L39: =MAX(0,L37-L38)
A40: Tape purchased this FY | B40: TB | C40: =C39 | D40: =D39-C39 | E40: =E39-D39 | F40: =F39-E39 | G40: =G39-F39 | H40: =H39-G39 | I40: =I39-H39 | J40: =J39-I39 | K40: =K39-J39 | L40: =L39-K39
A42: ALERT PRODUCTION AND SERVICES (USDF only — not shared with partner facilities)
A43: Alert Production cores | B43: cores | C43: ='Key Numbers'!$B$43 | D43: ='Key Numbers'!$B$43 | E43: ='Key Numbers'!$B$43 | F43: ='Key Numbers'!$B$43 | G43: ='Key Numbers'!$B$43 | H43: ='Key Numbers'!$B$43 | I43: ='Key Numbers'!$B$43 | J43: ='Key Numbers'!$B$43 | ... L43: ='Key Numbers'!$B$43
A44: Alert Production K8s nodes | B44: nodes | C44: =ROUNDUP(C43/'Key Numbers'!$B$45,0) | D44: =ROUNDUP(D43/'Key Numbers'!$B$45,0) | E44: =ROUNDUP(E43/'Key Numbers'!$B$45,0) | F44: =ROUNDUP(F43/'Key Numbers'!$B$45,0) | G44: =ROUNDUP(G43/'Key Numbers'!$B$45,0) | H44: =ROUNDUP(H43/'Key Numbers'!$B$45,0) | I44: =ROUNDUP(I43/'Key Numbers'!$B$45,0) | J44: =ROUNDUP(J43/'Key Numbers'!$B$45,0) | ... L44: =ROUNDUP(L43/'Key Numbers'!$B$45,0)
A45: DAC / LSP cores (share of DRP peak) | B45: cores | C45: =ROUND(C11*'Key Numbers'!$B$48,0) | D45: =ROUND(D11*'Key Numbers'!$B$48,0) | E45: =ROUND(E11*'Key Numbers'!$B$48,0) | F45: =ROUND(F11*'Key Numbers'!$B$48,0) | G45: =ROUND(G11*'Key Numbers'!$B$48,0) | H45: =ROUND(H11*'Key Numbers'!$B$48,0) | I45: =ROUND(I11*'Key Numbers'!$B$48,0) | J45: =ROUND(J11*'Key Numbers'!$B$48,0) | ... L45: =ROUND(L11*'Key Numbers'!$B$48,0)
A46: Staff cores | B46: cores | C46: =ROUND(C45*'Key Numbers'!$B$49,0) | D46: =ROUND(D45*'Key Numbers'!$B$49,0) | E46: =ROUND(E45*'Key Numbers'!$B$49,0) | F46: =ROUND(F45*'Key Numbers'!$B$49,0) | G46: =ROUND(G45*'Key Numbers'!$B$49,0) | H46: =ROUND(H45*'Key Numbers'!$B$49,0) | I46: =ROUND(I45*'Key Numbers'!$B$49,0) | J46: =ROUND(J45*'Key Numbers'!$B$49,0) | ... L46: =ROUND(L45*'Key Numbers'!$B$49,0)
A47: Interactive nodes | B47: nodes | C47: ='Key Numbers'!$B$66 | D47: ='Key Numbers'!$B$66 | E47: ='Key Numbers'!$B$66 | F47: ='Key Numbers'!$B$66 | G47: ='Key Numbers'!$B$66 | H47: ='Key Numbers'!$B$66 | I47: ='Key Numbers'!$B$66 | J47: ='Key Numbers'!$B$66 | ... L47: ='Key Numbers'!$B$66
A48: Service cores vs deployed K8s fleet | B48: % | C48: =(C43+C45+C46)/('Key Numbers'!$B$65*'Key Numbers'!$B$45) | D48: =(D43+D45+D46)/('Key Numbers'!$B$65*'Key Numbers'!$B$45) | E48: =(E43+E45+E46)/('Key Numbers'!$B$65*'Key Numbers'!$B$45) | F48: =(F43+F45+F46)/('Key Numbers'!$B$65*'Key Numbers'!$B$45) | G48: =(G43+G45+G46)/('Key Numbers'!$B$65*'Key Numbers'!$B$45) | H48: =(H43+H45+H46)/('Key Numbers'!$B$65*'Key Numbers'!$B$45) | I48: =(I43+I45+I46)/('Key Numbers'!$B$65*'Key Numbers'!$B$45) | J48: =(J43+J45+J46)/('Key Numbers'!$B$65*'Key Numbers'!$B$45) | ... L48: =(L43+L45+L46)/('Key Numbers'!$B$65*'Key Numbers'!$B$45)
A50: APDB / CASSANDRA (within the other on-floor allowance, not additional)
A51: APDB on floor | B51: TB | C51: ='Key Numbers'!$B$52/'Key Numbers'!$B$53*'Key Numbers'!$B$4*'Key Numbers'!$B$5*(COLUMN()-2) | D51: ='Key Numbers'!$B$52/'Key Numbers'!$B$53*'Key Numbers'!$B$4*'Key Numbers'!$B$5*(COLUMN()-2) | E51: ='Key Numbers'!$B$52/'Key Numbers'!$B$53*'Key Numbers'!$B$4*'Key Numbers'!$B$5*(COLUMN()-2) | F51: ='Key Numbers'!$B$52/'Key Numbers'!$B$53*'Key Numbers'!$B$4*'Key Numbers'!$B$5*(COLUMN()-2) | G51: ='Key Numbers'!$B$52/'Key Numbers'!$B$53*'Key Numbers'!$B$4*'Key Numbers'!$B$5*(COLUMN()-2) | H51: ='Key Numbers'!$B$52/'Key Numbers'!$B$53*'Key Numbers'!$B$4*'Key Numbers'!$B$5*(COLUMN()-2) | I51: ='Key Numbers'!$B$52/'Key Numbers'!$B$53*'Key Numbers'!$B$4*'Key Numbers'!$B$5*(COLUMN()-2) | J51: ='Key Numbers'!$B$52/'Key Numbers'!$B$53*'Key Numbers'!$B$4*'Key Numbers'!$B$5*(COLUMN()-2) | ... L51: ='Key Numbers'!$B$52/'Key Numbers'!$B$53*'Key Numbers'!$B$4*'Key Numbers'!$B$5*(COLUMN()-2)
A52: APDB off-site backup, cumulative | B52: TB | C52: ='Key Numbers'!$B$55/10*(COLUMN()-2) | D52: ='Key Numbers'!$B$55/10*(COLUMN()-2) | E52: ='Key Numbers'!$B$55/10*(COLUMN()-2) | F52: ='Key Numbers'!$B$55/10*(COLUMN()-2) | G52: ='Key Numbers'!$B$55/10*(COLUMN()-2) | H52: ='Key Numbers'!$B$55/10*(COLUMN()-2) | I52: ='Key Numbers'!$B$55/10*(COLUMN()-2) | J52: ='Key Numbers'!$B$55/10*(COLUMN()-2) | ... L52: ='Key Numbers'!$B$55/10*(COLUMN()-2)
A53: Cassandra nodes deployed | B53: nodes | C53: ='Key Numbers'!$B$54 | D53: ='Key Numbers'!$B$54 | E53: ='Key Numbers'!$B$54 | F53: ='Key Numbers'!$B$54 | G53: ='Key Numbers'!$B$54 | H53: ='Key Numbers'!$B$54 | I53: ='Key Numbers'!$B$54 | J53: ='Key Numbers'!$B$54 | ... L53: ='Key Numbers'!$B$54
A55: FILE / OBJECT COUNTS — capacity is not the only constraint
A56: Files written by this campaign | B56: millions | C56: ='Key Numbers'!$C$120/1000000*C7 | D56: ='Key Numbers'!$C$120/1000000*D7 | E56: ='Key Numbers'!$C$120/1000000*E7 | F56: ='Key Numbers'!$C$120/1000000*F7 | G56: ='Key Numbers'!$C$120/1000000*G7 | H56: ='Key Numbers'!$C$120/1000000*H7 | I56: ='Key Numbers'!$C$120/1000000*I7 | J56: ='Key Numbers'!$C$120/1000000*J7 | ... L56: ='Key Numbers'!$C$120/1000000*L7
A57: Files resident on floor | B57: millions | C57: =C56*('Key Numbers'!$B$27*(1-'Key Numbers'!$B$25/'Key Numbers'!$B$24)+'Key Numbers'!$B$25/'Key Numbers'!$B$24) | D57: =D56*('Key Numbers'!$B$27*(1-'Key Numbers'!$B$25/'Key Numbers'!$B$24)+'Key Numbers'!$B$25/'Key Numbers'!$B$24) | E57: =E56*('Key Numbers'!$B$27*(1-'Key Numbers'!$B$25/'Key Numbers'!$B$24)+'Key Numbers'!$B$25/'Key Numbers'!$B$24) | F57: =F56*('Key Numbers'!$B$27*(1-'Key Numbers'!$B$25/'Key Numbers'!$B$24)+'Key Numbers'!$B$25/'Key Numbers'!$B$24) | G57: =G56*('Key Numbers'!$B$27*(1-'Key Numbers'!$B$25/'Key Numbers'!$B$24)+'Key Numbers'!$B$25/'Key Numbers'!$B$24) | H57: =H56*('Key Numbers'!$B$27*(1-'Key Numbers'!$B$25/'Key Numbers'!$B$24)+'Key Numbers'!$B$25/'Key Numbers'!$B$24) | I57: =I56*('Key Numbers'!$B$27*(1-'Key Numbers'!$B$25/'Key Numbers'!$B$24)+'Key Numbers'!$B$25/'Key Numbers'!$B$24) | J57: =J56*('Key Numbers'!$B$27*(1-'Key Numbers'!$B$25/'Key Numbers'!$B$24)+'Key Numbers'!$B$25/'Key Numbers'!$B$24) | ... L57: =L56*('Key Numbers'!$B$27*(1-'Key Numbers'!$B$25/'Key Numbers'!$B$24)+'Key Numbers'!$B$25/'Key Numbers'!$B$24)
A59: BYTES WRITTEN and ON-FLOOR NEED are different quantities. The first is everything the campaign writes over its processing run. The second is what has to be resident on disk at once, and is what gets purchased: most intermediates are created and deleted during the run, so only the Key Numbers live-intermediate fraction is resident simultaneously, plus retained releases, raw data and prompt products, scaled by the other-on-floor allowance.
A60: The first loop year is the data preview as completed, comfortably inside the installed capacity.
A61: Tape is cumulative: raw data and every data release are preserved permanently, so the footprint only grows. Purchases start only once the footprint exceeds the tape capacity assumed available on Key Numbers. That capacity figure is UNVERIFIED: it comes from one hedged reading of a shared-facility accounting system, and the facility is multi-tenant, so owning media does not reserve library slots or drive bandwidth. Set it to 0 to see the conservative case, which roughly triples the tape purchase.
A62: Alert Production, DAC/RSP and interactive capacity are local-only obligations that partner facilities do not share; they run on the Kubernetes and interactive fleets rather than on batch, so they are shown against K8s capacity rather than added to batch purchases.
A63: User areas, APDB, sims and misc headroom are carried inside the other on-floor allowance on Key Numbers rather than as separate lines. Network/WAN is not modelled pending measured throughput figures. Every cell on this tab is a formula over Key Numbers.

Sheet Facility Split
A1: Scenario B — DRP split across data facilities (storage archived at USDF)
A2: Metric | B2: Unit | C2: LOY1 | D2: LOY2 | E2: LOY3 | F2: LOY4 | G2: LOY5 | H2: LOY6 | I2: LOY7 | J2: LOY8 | K2: LOY9 | L2: LOY10
A3: Fiscal Year | C3: FY2026 | D3: FY2027 | E3: FY2028 | F3: FY2029 | G3: FY2030 | H3: FY2031 | I3: FY2032 | J3: FY2033 | K3: FY2034 | L3: FY2035
A4: Milestone | C4: DP2 (actual) | D4: DR1 | E4: DR2 | F4: DR3 | G4: DR4 | H4: DR5 | I4: DR6 | J4: DR7 | K4: DR8 | L4: DR9
A6: SHARES BY YEAR (blue = edit; UK front-loads then tapers to its aggregate)
A7: USDF share (residual) | B7: % | C7: =1-C8-C9 | D7: =1-D8-D9 | E7: =1-E8-E9 | F7: =1-F8-F9 | G7: =1-G8-G9 | H7: =1-H8-H9 | I7: =1-I8-I9 | J7: =1-J8-J9 | ... L7: =1-L8-L9
A8: France / CC-IN2P3 share | B8: % | C8: 0 | D8: 0.4 | E8: 0.4 | F8: 0.4 | G8: 0.4 | H8: 0.4 | I8: 0.4 | J8: 0.4 | K8: 0.4 | L8: 0.4
A9: UK / UKDF share | B9: % | C9: 0 | D9: 0.4 | E9: 0.4 | F9: 0.24 | G9: 0.24 | H9: 0.24 | I9: 0.24 | J9: 0.24 | K9: 0.24 | L9: 0.24
A10: UK work-weighted aggregate (target on Key Numbers) | B10: =SUMPRODUCT(D9:L9,'All at USDF'!D7:L7)/SUM('All at USDF'!D7:L7) | D10: LOY1 shares are zero: DP2 was processed entirely at USDF.
A12: DRP WORK BY FACILITY — CORE-HOURS
A13: Total DRP core-hours | B13: core-hrs | C13: ='All at USDF'!C9 | D13: ='All at USDF'!D9 | E13: ='All at USDF'!E9 | F13: ='All at USDF'!F9 | G13: ='All at USDF'!G9 | H13: ='All at USDF'!H9 | I13: ='All at USDF'!I9 | J13: ='All at USDF'!J9 | ... L13: ='All at USDF'!L9
A14: USDF | B14: core-hrs | C14: =C13*C7 | D14: =D13*D7 | E14: =E13*E7 | F14: =F13*F7 | G14: =G13*G7 | H14: =H13*H7 | I14: =I13*I7 | J14: =J13*J7 | ... L14: =L13*L7
A15: France / CC-IN2P3 | B15: core-hrs | C15: =C13*C8 | D15: =D13*D8 | E15: =E13*E8 | F15: =F13*F8 | G15: =G13*G8 | H15: =H13*H8 | I15: =I13*I8 | J15: =J13*J8 | ... L15: =L13*L8
A16: UK / UKDF | B16: core-hrs | C16: =C13*C9 | D16: =D13*D9 | E16: =E13*E9 | F16: =F13*F9 | G16: =G13*G9 | H16: =H13*H9 | I16: =I13*I9 | J16: =J13*J9 | ... L16: =L13*L9
A18: DRP WORK BY FACILITY — NODE-DAYS (at the USDF 120-core reference node)
A19: USDF | B19: node-days | C19: =C14/(24*'Key Numbers'!$B$14) | D19: =D14/(24*'Key Numbers'!$B$14) | E19: =E14/(24*'Key Numbers'!$B$14) | F19: =F14/(24*'Key Numbers'!$B$14) | G19: =G14/(24*'Key Numbers'!$B$14) | H19: =H14/(24*'Key Numbers'!$B$14) | I19: =I14/(24*'Key Numbers'!$B$14) | J19: =J14/(24*'Key Numbers'!$B$14) | ... L19: =L14/(24*'Key Numbers'!$B$14)
A20: France / CC-IN2P3 | B20: node-days | C20: =C15/(24*'Key Numbers'!$B$14) | D20: =D15/(24*'Key Numbers'!$B$14) | E20: =E15/(24*'Key Numbers'!$B$14) | F20: =F15/(24*'Key Numbers'!$B$14) | G20: =G15/(24*'Key Numbers'!$B$14) | H20: =H15/(24*'Key Numbers'!$B$14) | I20: =I15/(24*'Key Numbers'!$B$14) | J20: =J15/(24*'Key Numbers'!$B$14) | ... L20: =L15/(24*'Key Numbers'!$B$14)
A21: UK / UKDF | B21: node-days | C21: =C16/(24*'Key Numbers'!$B$14) | D21: =D16/(24*'Key Numbers'!$B$14) | E21: =E16/(24*'Key Numbers'!$B$14) | F21: =F16/(24*'Key Numbers'!$B$14) | G21: =G16/(24*'Key Numbers'!$B$14) | H21: =H16/(24*'Key Numbers'!$B$14) | I21: =I16/(24*'Key Numbers'!$B$14) | J21: =J16/(24*'Key Numbers'!$B$14) | ... L21: =L16/(24*'Key Numbers'!$B$14)
A23: DRP WORK BY FACILITY — PEAK CONCURRENT CORES (in window)
A24: USDF | B24: cores | C24: =ROUND('All at USDF'!C11*C7,0) | D24: =ROUND('All at USDF'!D11*D7,0) | E24: =ROUND('All at USDF'!E11*E7,0) | F24: =ROUND('All at USDF'!F11*F7,0) | G24: =ROUND('All at USDF'!G11*G7,0) | H24: =ROUND('All at USDF'!H11*H7,0) | I24: =ROUND('All at USDF'!I11*I7,0) | J24: =ROUND('All at USDF'!J11*J7,0) | ... L24: =ROUND('All at USDF'!L11*L7,0)
A25: France / CC-IN2P3 | B25: cores | C25: =ROUND('All at USDF'!C11*C8,0) | D25: =ROUND('All at USDF'!D11*D8,0) | E25: =ROUND('All at USDF'!E11*E8,0) | F25: =ROUND('All at USDF'!F11*F8,0) | G25: =ROUND('All at USDF'!G11*G8,0) | H25: =ROUND('All at USDF'!H11*H8,0) | I25: =ROUND('All at USDF'!I11*I8,0) | J25: =ROUND('All at USDF'!J11*J8,0) | ... L25: =ROUND('All at USDF'!L11*L8,0)
A26: UK / UKDF | B26: cores | C26: =ROUND('All at USDF'!C11*C9,0) | D26: =ROUND('All at USDF'!D11*D9,0) | E26: =ROUND('All at USDF'!E11*E9,0) | F26: =ROUND('All at USDF'!F11*F9,0) | G26: =ROUND('All at USDF'!G11*G9,0) | H26: =ROUND('All at USDF'!H11*H9,0) | I26: =ROUND('All at USDF'!I11*I9,0) | J26: =ROUND('All at USDF'!J11*J9,0) | ... L26: =ROUND('All at USDF'!L11*L9,0)
A28: CAPACITY CHECKS
A29: USDF peak cores vs fleet (Milano-equivalent) | B29: % | C29: =C24/'Key Numbers'!$B$63 | D29: =D24/'Key Numbers'!$B$63 | E29: =E24/'Key Numbers'!$B$63 | F29: =F24/'Key Numbers'!$B$63 | G29: =G24/'Key Numbers'!$B$63 | H29: =H24/'Key Numbers'!$B$63 | I29: =I24/'Key Numbers'!$B$63 | J29: =J24/'Key Numbers'!$B$63 | ... L29: =L24/'Key Numbers'!$B$63
A30: UK required vs UK provisioned capacity | B30: % | C30: =C16/'Key Numbers'!$B$73 | D30: =D16/'Key Numbers'!$B$73 | E30: =E16/'Key Numbers'!$B$73 | F30: =F16/'Key Numbers'!$B$73 | G30: =G16/'Key Numbers'!$B$73 | H30: =H16/'Key Numbers'!$B$73 | I30: =I16/'Key Numbers'!$B$73 | J30: =J16/'Key Numbers'!$B$73 | ... L30: =L16/'Key Numbers'!$B$73
A31: France provisioned capacity not yet supplied.
A33: STORAGE IMPLICATIONS OF THE SPLIT
A34: Live intermediates held at France | B34: PB | C34: ='All at USDF'!C22*C8 | D34: ='All at USDF'!D22*D8 | E34: ='All at USDF'!E22*E8 | F34: ='All at USDF'!F22*F8 | G34: ='All at USDF'!G22*G8 | H34: ='All at USDF'!H22*H8 | I34: ='All at USDF'!I22*I8 | J34: ='All at USDF'!J22*J8 | ... L34: ='All at USDF'!L22*L8
A35: Live intermediates held at UK | B35: PB | C35: ='All at USDF'!C22*C9 | D35: ='All at USDF'!D22*D9 | E35: ='All at USDF'!E22*E9 | F35: ='All at USDF'!F22*F9 | G35: ='All at USDF'!G22*G9 | H35: ='All at USDF'!H22*H9 | I35: ='All at USDF'!I22*I9 | J35: ='All at USDF'!J22*J9 | ... L35: ='All at USDF'!L22*L9
A36: Retained releases archived at USDF (unchanged by split) | B36: PB | C36: ='All at USDF'!C23 | D36: ='All at USDF'!D23 | E36: ='All at USDF'!E23 | F36: ='All at USDF'!F23 | G36: ='All at USDF'!G23 | H36: ='All at USDF'!H23 | I36: ='All at USDF'!I23 | J36: ='All at USDF'!J23 | ... L36: ='All at USDF'!L23
A38: Partner facilities hold live intermediates for their share of the processing only; all release products transfer back to USDF for the archive. The per-year profiles are provisional — replace them with each partner's own plan when available.

Sheet Qserv
A1: Qserv — cluster specification and node projection
A3: CLUSTER SPECIFICATION (as of September 2026) — documentation, not calculation inputs
A4: Deployments | C4: 35-node Kubernetes production (serves DP2) + 35-node Kubernetes integration + 6-node Docker integration. Production and integration are the same size and hardware; their replication settings are not known to match
A5: CPU per node | C5: 1 x AMD EPYC 7543P, 32 cores / 64 hardware threads (SMT enabled)
A6: RAM per node | C6: 256 GB
A7: Storage per node | C7: Node-local NVMe, shared-nothing, no network storage in the query path: 12 of 24 slots populated = 32 TB raw; ZFS compression gives ~2x, so ~64 TB effective; filling the remaining slots would double raw capacity
A8: Internal network | C8: 100 GbE
A9: Nodes procured | C9: 102 across three procurement rounds, of which the deployments above are in service
A10: Replication | C10: Three-fold on production. The measured catalogue figures in this model come from a deployment observed running two-fold, so on-disk totals here are provisioning figures at three-fold, not measurements
A11: Relation to K8s fleet | C11: Most USDF Kubernetes nodes share this hardware configuration
A13: Metric | B13: Unit | C13: LOY1 | D13: LOY2 | E13: LOY3 | F13: LOY4 | G13: LOY5 | H13: LOY6 | I13: LOY7 | J13: LOY8 | K13: LOY9 | L13: LOY10
A14: Fiscal Year | C14: FY2026 | D14: FY2027 | E14: FY2028 | F14: FY2029 | G14: FY2030 | H14: FY2031 | I14: FY2032 | J14: FY2033 | K14: FY2034 | L14: FY2035
A15: Milestone | C15: DP2 | D15: DR1 | E15: DR2 | F15: DR3 | G15: DR4 | H15: DR5 | I15: DR6 | J15: DR7 | K15: DR8 | L15: DR9
A17: CATALOG SIZES BY DATA RELEASE (first column is the data preview, measured not modelled)
A18: Objects | B18: billions | D18: 27.5 | E18: 32.5 | F18: 35.7 | G18: 38.2 | H18: 40.3 | I18: 42.2 | J18: 43.8 | K18: 45.3 | L18: 46.4
A19: Sources | B19: billions | D19: 901 | E19: 1800 | F19: 2700 | G19: 3600 | H19: 4510 | I19: 5410 | J19: 6310 | K19: 7210 | L19: 8110
A20: Forced sources | B20: billions | D20: 2910 | E20: 6870 | F20: 11300 | G20: 16100 | H20: 21300 | I20: 26700 | J20: 32400 | K20: 38300 | L20: 44100
A21: row-size inflation vs DR1 | B21: x | D21: =(1+'Key Numbers'!$B$84)^(COLUMN()-4) | E21: =(1+'Key Numbers'!$B$84)^(COLUMN()-4) | F21: =(1+'Key Numbers'!$B$84)^(COLUMN()-4) | G21: =(1+'Key Numbers'!$B$84)^(COLUMN()-4) | H21: =(1+'Key Numbers'!$B$84)^(COLUMN()-4) | I21: =(1+'Key Numbers'!$B$84)^(COLUMN()-4) | J21: =(1+'Key Numbers'!$B$84)^(COLUMN()-4) | K21: =(1+'Key Numbers'!$B$84)^(COLUMN()-4) | L21: =(1+'Key Numbers'!$B$84)^(COLUMN()-4)
A23: QSERV DATABASE SIZE
A24: Catalogue, logical uncompressed, one copy | B24: TB | D24: =((D18*('Key Numbers'!$B$80+'Key Numbers'!$B$81)+D19*'Key Numbers'!$B$82)*D21+D20*'Key Numbers'!$B$83)*1000000000/1000000000000 | E24: =((E18*('Key Numbers'!$B$80+'Key Numbers'!$B$81)+E19*'Key Numbers'!$B$82)*E21+E20*'Key Numbers'!$B$83)*1000000000/1000000000000 | F24: =((F18*('Key Numbers'!$B$80+'Key Numbers'!$B$81)+F19*'Key Numbers'!$B$82)*F21+F20*'Key Numbers'!$B$83)*1000000000/1000000000000 | G24: =((G18*('Key Numbers'!$B$80+'Key Numbers'!$B$81)+G19*'Key Numbers'!$B$82)*G21+G20*'Key Numbers'!$B$83)*1000000000/1000000000000 | H24: =((H18*('Key Numbers'!$B$80+'Key Numbers'!$B$81)+H19*'Key Numbers'!$B$82)*H21+H20*'Key Numbers'!$B$83)*1000000000/1000000000000 | I24: =((I18*('Key Numbers'!$B$80+'Key Numbers'!$B$81)+I19*'Key Numbers'!$B$82)*I21+I20*'Key Numbers'!$B$83)*1000000000/1000000000000 | J24: =((J18*('Key Numbers'!$B$80+'Key Numbers'!$B$81)+J19*'Key Numbers'!$B$82)*J21+J20*'Key Numbers'!$B$83)*1000000000/1000000000000 | K24: =((K18*('Key Numbers'!$B$80+'Key Numbers'!$B$81)+K19*'Key Numbers'!$B$82)*K21+K20*'Key Numbers'!$B$83)*1000000000/1000000000000 | L24: =((L18*('Key Numbers'!$B$80+'Key Numbers'!$B$81)+L19*'Key Numbers'!$B$82)*L21+L20*'Key Numbers'!$B$83)*1000000000/1000000000000
A25: Object table, replicated and compressed | B25: TB | D25: =D18*1000000000*'Key Numbers'!$B$80*'Key Numbers'!$B$85*'Key Numbers'!$B$77/1000000000000 | E25: =E18*1000000000*'Key Numbers'!$B$80*'Key Numbers'!$B$85*'Key Numbers'!$B$77/1000000000000 | F25: =F18*1000000000*'Key Numbers'!$B$80*'Key Numbers'!$B$85*'Key Numbers'!$B$77/1000000000000 | G25: =G18*1000000000*'Key Numbers'!$B$80*'Key Numbers'!$B$85*'Key Numbers'!$B$77/1000000000000 | H25: =H18*1000000000*'Key Numbers'!$B$80*'Key Numbers'!$B$85*'Key Numbers'!$B$77/1000000000000 | I25: =I18*1000000000*'Key Numbers'!$B$80*'Key Numbers'!$B$85*'Key Numbers'!$B$77/1000000000000 | J25: =J18*1000000000*'Key Numbers'!$B$80*'Key Numbers'!$B$85*'Key Numbers'!$B$77/1000000000000 | K25: =K18*1000000000*'Key Numbers'!$B$80*'Key Numbers'!$B$85*'Key Numbers'!$B$77/1000000000000 | L25: =L18*1000000000*'Key Numbers'!$B$80*'Key Numbers'!$B$85*'Key Numbers'!$B$77/1000000000000
A26: Worker database on disk, this release (replicated, compressed) | B26: TB | C26: ='Key Numbers'!$B$88*'Key Numbers'!$B$77 | D26: =D24*'Key Numbers'!$B$85*(1+'Key Numbers'!$B$78)*'Key Numbers'!$B$77 | E26: =E24*'Key Numbers'!$B$85*(1+'Key Numbers'!$B$78)*'Key Numbers'!$B$77 | F26: =F24*'Key Numbers'!$B$85*(1+'Key Numbers'!$B$78)*'Key Numbers'!$B$77 | G26: =G24*'Key Numbers'!$B$85*(1+'Key Numbers'!$B$78)*'Key Numbers'!$B$77 | H26: =H24*'Key Numbers'!$B$85*(1+'Key Numbers'!$B$78)*'Key Numbers'!$B$77 | I26: =I24*'Key Numbers'!$B$85*(1+'Key Numbers'!$B$78)*'Key Numbers'!$B$77 | J26: =J24*'Key Numbers'!$B$85*(1+'Key Numbers'!$B$78)*'Key Numbers'!$B$77 | K26: =K24*'Key Numbers'!$B$85*(1+'Key Numbers'!$B$78)*'Key Numbers'!$B$77 | L26: =L24*'Key Numbers'!$B$85*(1+'Key Numbers'!$B$78)*'Key Numbers'!$B$77
A27: Worker database, retention window | B27: TB | C27: =C26 | D27: =C26+D26 | E27: =C26+D26+E26 | F27: =D26+E26+F26 | G27: =E26+F26+G26 | H27: =F26+G26+H26 | I27: =G26+H26+I26 | J27: =H26+I26+J26 | K27: =I26+J26+K26 | L27: =J26+K26+L26
A28: same in PB | B28: PB | C28: =C27/1000 | D28: =D27/1000 | E28: =E27/1000 | F28: =F27/1000 | G28: =G27/1000 | H28: =H27/1000 | I28: =I27/1000 | J28: =J27/1000 | ... L28: =L27/1000
A30: CALIBRATION AGAINST MEASURED DATA
A31: Worker database per copy | B31: TB | C31: =C26/'Key Numbers'!$B$77 | D31: =D26/'Key Numbers'!$B$77 | E31: =E26/'Key Numbers'!$B$77 | F31: =F26/'Key Numbers'!$B$77 | G31: =G26/'Key Numbers'!$B$77 | H31: =H26/'Key Numbers'!$B$77 | I31: =I26/'Key Numbers'!$B$77 | J31: =J26/'Key Numbers'!$B$77 | ... L31: =L26/'Key Numbers'!$B$77
A32: As a multiple of the measured data preview | B32: x | C32: =C31/'Key Numbers'!$B$88 | D32: =D31/'Key Numbers'!$B$88 | E32: =E31/'Key Numbers'!$B$88 | F32: =F31/'Key Numbers'!$B$88 | G32: =G31/'Key Numbers'!$B$88 | H32: =H31/'Key Numbers'!$B$88 | I32: =I31/'Key Numbers'!$B$88 | J32: =J31/'Key Numbers'!$B$88 | ... L32: =L31/'Key Numbers'!$B$88
A33: Visits as a multiple of the data preview | B33: x | C33: ='All at USDF'!C7/('Key Numbers'!$B$92/('Key Numbers'!$B$4*'Key Numbers'!$B$5)) | D33: ='All at USDF'!D7/('Key Numbers'!$B$92/('Key Numbers'!$B$4*'Key Numbers'!$B$5)) | E33: ='All at USDF'!E7/('Key Numbers'!$B$92/('Key Numbers'!$B$4*'Key Numbers'!$B$5)) | F33: ='All at USDF'!F7/('Key Numbers'!$B$92/('Key Numbers'!$B$4*'Key Numbers'!$B$5)) | G33: ='All at USDF'!G7/('Key Numbers'!$B$92/('Key Numbers'!$B$4*'Key Numbers'!$B$5)) | H33: ='All at USDF'!H7/('Key Numbers'!$B$92/('Key Numbers'!$B$4*'Key Numbers'!$B$5)) | I33: ='All at USDF'!I7/('Key Numbers'!$B$92/('Key Numbers'!$B$4*'Key Numbers'!$B$5)) | J33: ='All at USDF'!J7/('Key Numbers'!$B$92/('Key Numbers'!$B$4*'Key Numbers'!$B$5)) | ... L33: ='All at USDF'!L7/('Key Numbers'!$B$92/('Key Numbers'!$B$4*'Key Numbers'!$B$5))
A34: Independent DR1 estimate, per copy (midpoint) | B34: TB | D34: =('Key Numbers'!$B$86+'Key Numbers'!$B$87)/2*1000
A35: Model as a multiple of that estimate | B35: x | D35: =D31/D34
A37: NODE PROJECTION
A38: Data per node (drive-density ramp) | B38: TB/node | C38: 43.2 | D38: 43.2 | E38: 86.4 | F38: 86.4 | G38: 86.4 | H38: 86.4 | I38: 172.8 | J38: 172.8 | K38: 172.8 | L38: 172.8
A39: QSERV NODES NEEDED | B39: nodes | C39: =ROUNDUP(C27/C38,0) | D39: =ROUNDUP(D27/D38,0) | E39: =ROUNDUP(E27/E38,0) | F39: =ROUNDUP(F27/F38,0) | G39: =ROUNDUP(G27/G38,0) | H39: =ROUNDUP(H27/H38,0) | I39: =ROUNDUP(I27/I38,0) | J39: =ROUNDUP(J27/J38,0) | ... L39: =ROUNDUP(L27/L38,0)
A40: Qserv nodes deployed today | B40: nodes | C40: ='Key Numbers'!$B$76 | D40: ='Key Numbers'!$B$76 | E40: ='Key Numbers'!$B$76 | F40: ='Key Numbers'!$B$76 | G40: ='Key Numbers'!$B$76 | H40: ='Key Numbers'!$B$76 | I40: ='Key Numbers'!$B$76 | J40: ='Key Numbers'!$B$76 | ... L40: ='Key Numbers'!$B$76
A41: Surplus / (gap) | B41: nodes | C41: =C40-C39 | D41: =D40-D39 | E41: =E40-E39 | F41: =F40-F39 | G41: =G40-G39 | H41: =H40-H39 | I41: =I40-I39 | J41: =J40-J39 | ... L41: =L40-L39
A43: Database size = catalogue rows x row sizes x compression x replication, summed over the retention window. Node count divides that by the assumed usable TB per node, which ramps as drives densify. Replication is already included, so these are physical nodes.
A44: STRUCTURE: the catalogue series are data-release scale — the first entry is DR1, one full survey-year — so they sit one column to the right of the data-preview column. No modelled catalogue counts exist for the preview, so that column is anchored on a measured figure instead. Both the compression factor and the replication factor are applied on top of the logical row, so the on-disk row is what a purchase has to cover.
A45: CAVEAT: the calibration rows compare the modelled catalogue against the one measured point available. They are NOT expected to match exactly — the data preview covers a small sky area, so its object count is far below a data release, while sources scale with visits. They are there to keep the modelled figures next to measurement rather than to validate them. The modelled data-release columns rest on logical row sizes that have never been checked against a measured catalogue; until per-table row counts are available, treat them as an upper bound.
A46: The replication factor and the row-size calibration are the two levers that move every catalogue figure. Both are marked on Key Numbers.
A47: STRUCTURE: row sizes widen between releases, so the object and source terms carry the compounding inflation factor shown in the catalogue block above. Forced sources are excluded from it because that schema is fixed. The exponent counts releases since DR1, so a change of release cadence changes how far this compounds inside the ten years, not how fast it compounds per release.
A48: CAVEAT: the last two calibration rows appear only in the DR1 column. They compare the modelled catalogue against an independently stated DR1 planning range, which drives nothing in this workbook. A multiple materially below 1 means the model is sizing under that expectation; treat a gap as unresolved rather than as either figure being confirmed.
A49: CAVEAT: filesystem compression is applied once, on the capacity side, inside the data-per-node ramp. The row-size factor above must therefore stay on an uncompressed basis. Applying a compression ratio in both places understates the node count by roughly a factor of three.

Sheet DF Template
A1: Per-Facility Calculator — fill in the yellow cells for your facility
A3: Loop year to evaluate (1-10) | B3: 2 | C3: LOY2 = FY2027 = DR1
B5: USDF | C5: France (CC-IN2P3) | D5: UK (UKDF) | E5: Your DF
A6: DRP share (aggregate; per-year on Facility Split) | B6: ='Key Numbers'!$B$72 | C6: ='Key Numbers'!$B$70 | D6: ='Key Numbers'!$B$71 | E6: 0.1
A7: Cores per node | B7: ='Key Numbers'!$B$14 | C7: 120 | D7: 120 | E7: 128
A8: Processing window (days) | B8: ='Key Numbers'!$B$15 | C8: ='Key Numbers'!$B$15 | D8: ='Key Numbers'!$B$15 | E8: 200
A9: Provisioned capacity (core-hrs/yr) | B9: ='Key Numbers'!$B$63*'Key Numbers'!$B$15*24 | D9: ='Key Numbers'!$B$73 | E9: 10000000
A10: COMPUTED
A11: Total DRP work for that year — core-hours | B11: =INDEX('All at USDF'!$C$9:$L$9,1,$B$3) | C11: =INDEX('All at USDF'!$C$9:$L$9,1,$B$3) | D11: =INDEX('All at USDF'!$C$9:$L$9,1,$B$3) | E11: =INDEX('All at USDF'!$C$9:$L$9,1,$B$3)
A12: Your facility — core-hours | B12: =B11*B6 | C12: =C11*C6 | D12: =D11*D6 | E12: =E11*E6
A13: Your facility — node-days | B13: =B12/(24*B7) | C13: =C12/(24*C7) | D13: =D12/(24*D7) | E13: =E12/(24*E7)
A14: Your facility — peak concurrent cores | B14: =ROUND(B12/(B8*24)*'Key Numbers'!$B$16,0) | C14: =ROUND(C12/(C8*24)*'Key Numbers'!$B$16,0) | D14: =ROUND(D12/(D8*24)*'Key Numbers'!$B$16,0) | E14: =ROUND(E12/(E8*24)*'Key Numbers'!$B$16,0)
A15: Nodes needed | B15: =ROUNDUP(B14/B7,0) | C15: =ROUNDUP(C14/C7,0) | D15: =ROUNDUP(D14/D7,0) | E15: =ROUNDUP(E14/E7,0)
A16: Utilization vs provisioned | B16: =IF(B9="","",B12/B9) | C16: =IF(C9="","",C12/C9) | D16: =IF(D9="","",D12/D9) | E16: =IF(E9="","",E12/E9)
A18: The 'Your DF' column holds example values (10% share, 128-core nodes, 10M core-hrs/yr) — replace with your facility's numbers. Yellow = edit, green = linked to Key Numbers. USDF provisioned capacity uses Milano-equivalent cores. The USDF-only RSP surcharge is deliberately excluded from this tab.

Sheet Cost Inputs
A1: COST INPUTS (reference tab) — costs only
A2: Sizing and data-product numbers are NOT duplicated here — they live on Key Numbers. Blue = raw input · Yellow = key assumption. Only the Pricing Forecast reads this tab.
A3: UNIT COSTS
A4: Torino batch node (768 GB RAM) | B4: 89355 | C4: $/node | G4: current quote; assumed for all future batch purchases
A5: K8s / Qserv-class node (EPYC 7543P) | B5: 30866 | C5: $/node | G5: same hardware class serves both roles
A6: Ceph usable disk | B6: 235.052 | C6: $/TB | G6: enclosure cost divided by usable TB per enclosure
A7: Tape / archive | B7: 8.625 | C7: $/TB | G7: archive and backup estimate
A8: Hosting per node per year | B8: 566 | C8: $/node-yr | G8: carried from an earlier agreement and not re-quoted; the least well-founded figure on this tab
A9: Overhead on hardware | B9: 0.14 | C9: % | G9: applied to the hardware subtotal
A10: Overhead, fixed annual | B10: 150000 | C10: $/yr
A11: Annual price change | B11: 0 | C11: %/yr | G11: 0% holds prices flat; set negative for price falls
A13: LIFECYCLE AND GROWTH
A14: Compute hardware lifetime | B14: 5 | C14: years | G14: a cohort bought in FY_x is replaced in FY_x + lifetime
A15: Storage hardware lifetime | B15: 5 | C15: years | G15: disk capacity is re-bought after this many years
A16: K8s annual growth | B16: 0.05 | C16: fraction | G16: services growth, applied to the deployed K8s base on Key Numbers
A18: HISTORIC PURCHASES BY FISCAL YEAR (drives cohort refresh)
B19: FY2021 | C19: FY2022 | D19: FY2023 | E19: FY2024 | F19: FY2025
A20: Batch nodes purchased | B20: 0 | C20: 0 | D20: 72 | E20: 50 | F20: 35 | G20: the final-year count is assumed rather than recorded
A21: Qserv nodes purchased | B21: 0 | C21: 0 | D21: 47 | E21: 55 | F21: 0
A22: K8s nodes purchased | B22: 0 | C22: 16 | D22: 32 | E22: 30 | F22: 0
A24: CURRENT-YEAR ACTUAL REQUESTS
A25: Batch nodes requested | B25: 0 | C25: nodes | G25: zero — the existing fleet covers FY2026
A26: K8s nodes requested | B26: 24 | C26: nodes
A27: K8s cost | B27: 740784 | C27: $
A28: Disk requested | B28: 10082 | C28: TB | G28: usable Ceph
A29: Disk cost | B29: 2369794 | C29: $
A30: Archive requested | B30: 5000 | C30: TB
A31: Archive cost | B31: 43125 | C31: $
A33: These are the only cost numbers in the workbook. Everything the forecast needs about data volumes, core-hours, fleet size or facility shares is read from the Key Numbers tab.
A34: Hosting and overhead are carried from an earlier agreement and were not re-quoted; treat them as the least well-founded figures here.

Sheet USDF Pricing Forecast
A1: USDF PRICING FORECAST — everything at USDF (partner facility prices unknown)
A2: Metric | B2: Unit | C2: FY2026 | D2: FY2027 | E2: FY2028 | F2: FY2029 | G2: FY2030 | H2: FY2031 | I2: FY2032 | J2: FY2033 | K2: FY2034 | L2: FY2035 | M2: 10-yr Total
C3: DP2 (actual) | D3: DR1 | E3: DR2 | F3: DR3 | G3: DR4 | H3: DR5 | I3: DR6 | J3: DR7 | K3: DR8 | L3: DR9
A5: DEMAND — linked from All at USDF and Qserv, never re-derived here
A6: Survey years of input processed | B6: years | C6: ='All at USDF'!C7 | D6: ='All at USDF'!D7 | E6: ='All at USDF'!E7 | F6: ='All at USDF'!F7 | G6: ='All at USDF'!G7 | H6: ='All at USDF'!H7 | I6: ='All at USDF'!I7 | J6: ='All at USDF'!J7 | ... L6: ='All at USDF'!L7
A7: DRP core-hours | B7: core-hrs | C7: ='All at USDF'!C9 | D7: ='All at USDF'!D9 | E7: ='All at USDF'!E9 | F7: ='All at USDF'!F9 | G7: ='All at USDF'!G9 | H7: ='All at USDF'!H9 | I7: ='All at USDF'!I9 | J7: ='All at USDF'!J9 | ... L7: ='All at USDF'!L9
A8: Peak concurrent cores (Milano-equivalent) | B8: cores | C8: ='All at USDF'!C11 | D8: ='All at USDF'!D11 | E8: ='All at USDF'!E11 | F8: ='All at USDF'!F11 | G8: ='All at USDF'!G11 | H8: ='All at USDF'!H11 | I8: ='All at USDF'!I11 | J8: ='All at USDF'!J11 | ... L8: ='All at USDF'!L11
A10: BATCH COMPUTE PURCHASES
A11: Cumulative Torino needed beyond current fleet | B11: nodes | C11: =MAX(0,ROUNDUP((C8-'Key Numbers'!$B$63)/('Key Numbers'!$B$14*'Key Numbers'!$B$62),0)) | D11: =MAX(0,ROUNDUP((D8-'Key Numbers'!$B$63)/('Key Numbers'!$B$14*'Key Numbers'!$B$62),0)) | E11: =MAX(0,ROUNDUP((E8-'Key Numbers'!$B$63)/('Key Numbers'!$B$14*'Key Numbers'!$B$62),0)) | F11: =MAX(0,ROUNDUP((F8-'Key Numbers'!$B$63)/('Key Numbers'!$B$14*'Key Numbers'!$B$62),0)) | G11: =MAX(0,ROUNDUP((G8-'Key Numbers'!$B$63)/('Key Numbers'!$B$14*'Key Numbers'!$B$62),0)) | H11: =MAX(0,ROUNDUP((H8-'Key Numbers'!$B$63)/('Key Numbers'!$B$14*'Key Numbers'!$B$62),0)) | I11: =MAX(0,ROUNDUP((I8-'Key Numbers'!$B$63)/('Key Numbers'!$B$14*'Key Numbers'!$B$62),0)) | J11: =MAX(0,ROUNDUP((J8-'Key Numbers'!$B$63)/('Key Numbers'!$B$14*'Key Numbers'!$B$62),0)) | ... L11: =MAX(0,ROUNDUP((L8-'Key Numbers'!$B$63)/('Key Numbers'!$B$14*'Key Numbers'!$B$62),0))
A12: Growth purchases this FY | B12: nodes | C12: ='Cost Inputs'!$B$25 | D12: =D11-C11 | E12: =E11-D11 | F12: =F11-E11 | G12: =G11-F11 | H12: =H11-G11 | I12: =I11-H11 | J12: =J11-I11 | K12: =K11-J11 | L12: =L11-K11 | M12: =SUM(C12:L12)
A13: Cohort refresh due this FY | B13: nodes | C13: =IF(AND(COLUMN()+2026-3-'Cost Inputs'!$B$14>=2021,COLUMN()+2026-3-'Cost Inputs'!$B$14<=2025),INDEX('Cost Inputs'!$B$20:$F$20,1,COLUMN()+2026-3-'Cost Inputs'!$B$14-2020),0)+IF(COLUMN()-2>'Cost Inputs'!$B$14,INDEX($C$14:$L$14,1,COLUMN()-2-'Cost Inputs'!$B$14),0) | D13: =IF(AND(COLUMN()+2026-3-'Cost Inputs'!$B$14>=2021,COLUMN()+2026-3-'Cost Inputs'!$B$14<=2025),INDEX('Cost Inputs'!$B$20:$F$20,1,COLUMN()+2026-3-'Cost Inputs'!$B$14-2020),0)+IF(COLUMN()-2>'Cost Inputs'!$B$14,INDEX($C$14:$L$14,1,COLUMN()-2-'Cost Inputs'!$B$14),0) | E13: =IF(AND(COLUMN()+2026-3-'Cost Inputs'!$B$14>=2021,COLUMN()+2026-3-'Cost Inputs'!$B$14<=2025),INDEX('Cost Inputs'!$B$20:$F$20,1,COLUMN()+2026-3-'Cost Inputs'!$B$14-2020),0)+IF(COLUMN()-2>'Cost Inputs'!$B$14,INDEX($C$14:$L$14,1,COLUMN()-2-'Cost Inputs'!$B$14),0) | F13: =IF(AND(COLUMN()+2026-3-'Cost Inputs'!$B$14>=2021,COLUMN()+2026-3-'Cost Inputs'!$B$14<=2025),INDEX('Cost Inputs'!$B$20:$F$20,1,COLUMN()+2026-3-'Cost Inputs'!$B$14-2020),0)+IF(COLUMN()-2>'Cost Inputs'!$B$14,INDEX($C$14:$L$14,1,COLUMN()-2-'Cost Inputs'!$B$14),0) | G13: =IF(AND(COLUMN()+2026-3-'Cost Inputs'!$B$14>=2021,COLUMN()+2026-3-'Cost Inputs'!$B$14<=2025),INDEX('Cost Inputs'!$B$20:$F$20,1,COLUMN()+2026-3-'Cost Inputs'!$B$14-2020),0)+IF(COLUMN()-2>'Cost Inputs'!$B$14,INDEX($C$14:$L$14,1,COLUMN()-2-'Cost Inputs'!$B$14),0) | H13: =IF(AND(COLUMN()+2026-3-'Cost Inputs'!$B$14>=2021,COLUMN()+2026-3-'Cost Inputs'!$B$14<=2025),INDEX('Cost Inputs'!$B$20:$F$20,1,COLUMN()+2026-3-'Cost Inputs'!$B$14-2020),0)+IF(COLUMN()-2>'Cost Inputs'!$B$14,INDEX($C$14:$L$14,1,COLUMN()-2-'Cost Inputs'!$B$14),0) | I13: =IF(AND(COLUMN()+2026-3-'Cost Inputs'!$B$14>=2021,COLUMN()+2026-3-'Cost Inputs'!$B$14<=2025),INDEX('Cost Inputs'!$B$20:$F$20,1,COLUMN()+2026-3-'Cost Inputs'!$B$14-2020),0)+IF(COLUMN()-2>'Cost Inputs'!$B$14,INDEX($C$14:$L$14,1,COLUMN()-2-'Cost Inputs'!$B$14),0) | J13: =IF(AND(COLUMN()+2026-3-'Cost Inputs'!$B$14>=2021,COLUMN()+2026-3-'Cost Inputs'!$B$14<=2025),INDEX('Cost Inputs'!$B$20:$F$20,1,COLUMN()+2026-3-'Cost Inputs'!$B$14-2020),0)+IF(COLUMN()-2>'Cost Inputs'!$B$14,INDEX($C$14:$L$14,1,COLUMN()-2-'Cost Inputs'!$B$14),0) | ... L13: =IF(AND(COLUMN()+2026-3-'Cost Inputs'!$B$14>=2021,COLUMN()+2026-3-'Cost Inputs'!$B$14<=2025),INDEX('Cost Inputs'!$B$20:$F$20,1,COLUMN()+2026-3-'Cost Inputs'!$B$14-2020),0)+IF(COLUMN()-2>'Cost Inputs'!$B$14,INDEX($C$14:$L$14,1,COLUMN()-2-'Cost Inputs'!$B$14),0) | M13: =SUM(C13:L13)
A14: Batch nodes purchased | B14: nodes | C14: =C12+C13 | D14: =D12+D13 | E14: =E12+E13 | F14: =F12+F13 | G14: =G12+G13 | H14: =H12+H13 | I14: =I12+I13 | J14: =J12+J13 | ... L14: =L12+L13 | M14: =SUM(C14:L14)
A15: Batch compute cost | B15: $ | C15: =C14*'Cost Inputs'!$B$4*(1+'Cost Inputs'!$B$11)^(0) | D15: =D14*'Cost Inputs'!$B$4*(1+'Cost Inputs'!$B$11)^(1) | E15: =E14*'Cost Inputs'!$B$4*(1+'Cost Inputs'!$B$11)^(2) | F15: =F14*'Cost Inputs'!$B$4*(1+'Cost Inputs'!$B$11)^(3) | G15: =G14*'Cost Inputs'!$B$4*(1+'Cost Inputs'!$B$11)^(4) | H15: =H14*'Cost Inputs'!$B$4*(1+'Cost Inputs'!$B$11)^(5) | I15: =I14*'Cost Inputs'!$B$4*(1+'Cost Inputs'!$B$11)^(6) | J15: =J14*'Cost Inputs'!$B$4*(1+'Cost Inputs'!$B$11)^(7) | K15: =K14*'Cost Inputs'!$B$4*(1+'Cost Inputs'!$B$11)^(8) | L15: =L14*'Cost Inputs'!$B$4*(1+'Cost Inputs'!$B$11)^(9) | M15: =SUM(C15:L15)
A17: DISK AND TAPE PURCHASES
A18: On-floor disk need (from All at USDF) | B18: TB | C18: ='All at USDF'!C29 | D18: ='All at USDF'!D29 | E18: ='All at USDF'!E29 | F18: ='All at USDF'!F29 | G18: ='All at USDF'!G29 | H18: ='All at USDF'!H29 | I18: ='All at USDF'!I29 | J18: ='All at USDF'!J29 | ... L18: ='All at USDF'!L29
A19: Disk installed + purchased to date | B19: TB | C19: ='Key Numbers'!$B$64*1000+C20 | D19: =C19+D20 | E19: =D19+E20 | F19: =E19+F20 | G19: =F19+G20 | H19: =G19+H20 | I19: =H19+I20 | J19: =I19+J20 | K19: =J19+K20 | L19: =K19+L20
A20: Disk purchased this FY (new capacity) | B20: TB | C20: ='Cost Inputs'!$B$28 | D20: =MAX(0,D18-C19) | E20: =MAX(0,E18-D19) | F20: =MAX(0,F18-E19) | G20: =MAX(0,G18-F19) | H20: =MAX(0,H18-G19) | I20: =MAX(0,I18-H19) | J20: =MAX(0,J18-I19) | K20: =MAX(0,K18-J19) | L20: =MAX(0,L18-K19) | M20: =SUM(C20:L20)
A21: Disk re-buy (end of storage lifetime) | B21: TB | C21: 0 | D21: =IF(COLUMN()-2>'Cost Inputs'!$B$15,INDEX($C$20:$L$20,1,COLUMN()-2-'Cost Inputs'!$B$15),0) | E21: =IF(COLUMN()-2>'Cost Inputs'!$B$15,INDEX($C$20:$L$20,1,COLUMN()-2-'Cost Inputs'!$B$15),0) | F21: =IF(COLUMN()-2>'Cost Inputs'!$B$15,INDEX($C$20:$L$20,1,COLUMN()-2-'Cost Inputs'!$B$15),0) | G21: =IF(COLUMN()-2>'Cost Inputs'!$B$15,INDEX($C$20:$L$20,1,COLUMN()-2-'Cost Inputs'!$B$15),0) | H21: =IF(COLUMN()-2>'Cost Inputs'!$B$15,INDEX($C$20:$L$20,1,COLUMN()-2-'Cost Inputs'!$B$15),0) | I21: =IF(COLUMN()-2>'Cost Inputs'!$B$15,INDEX($C$20:$L$20,1,COLUMN()-2-'Cost Inputs'!$B$15),0) | J21: =IF(COLUMN()-2>'Cost Inputs'!$B$15,INDEX($C$20:$L$20,1,COLUMN()-2-'Cost Inputs'!$B$15),0) | K21: =IF(COLUMN()-2>'Cost Inputs'!$B$15,INDEX($C$20:$L$20,1,COLUMN()-2-'Cost Inputs'!$B$15),0) | L21: =IF(COLUMN()-2>'Cost Inputs'!$B$15,INDEX($C$20:$L$20,1,COLUMN()-2-'Cost Inputs'!$B$15),0) | M21: =SUM(C21:L21)
A22: Disk cost | B22: $ | C22: ='Cost Inputs'!$B$29 | D22: =(D20+D21)*'Cost Inputs'!$B$6*(1+'Cost Inputs'!$B$11)^(1) | E22: =(E20+E21)*'Cost Inputs'!$B$6*(1+'Cost Inputs'!$B$11)^(2) | F22: =(F20+F21)*'Cost Inputs'!$B$6*(1+'Cost Inputs'!$B$11)^(3) | G22: =(G20+G21)*'Cost Inputs'!$B$6*(1+'Cost Inputs'!$B$11)^(4) | H22: =(H20+H21)*'Cost Inputs'!$B$6*(1+'Cost Inputs'!$B$11)^(5) | I22: =(I20+I21)*'Cost Inputs'!$B$6*(1+'Cost Inputs'!$B$11)^(6) | J22: =(J20+J21)*'Cost Inputs'!$B$6*(1+'Cost Inputs'!$B$11)^(7) | K22: =(K20+K21)*'Cost Inputs'!$B$6*(1+'Cost Inputs'!$B$11)^(8) | L22: =(L20+L21)*'Cost Inputs'!$B$6*(1+'Cost Inputs'!$B$11)^(9) | M22: =SUM(C22:L22)
A23: Tape / archive added (from All at USDF) | B23: TB | C23: ='Cost Inputs'!$B$30 | D23: ='All at USDF'!D40 | E23: ='All at USDF'!E40 | F23: ='All at USDF'!F40 | G23: ='All at USDF'!G40 | H23: ='All at USDF'!H40 | I23: ='All at USDF'!I40 | J23: ='All at USDF'!J40 | K23: ='All at USDF'!K40 | L23: ='All at USDF'!L40 | M23: =SUM(C23:L23)
A24: Tape cost | B24: $ | C24: ='Cost Inputs'!$B$31 | D24: =D23*'Cost Inputs'!$B$7*(1+'Cost Inputs'!$B$11)^(1) | E24: =E23*'Cost Inputs'!$B$7*(1+'Cost Inputs'!$B$11)^(2) | F24: =F23*'Cost Inputs'!$B$7*(1+'Cost Inputs'!$B$11)^(3) | G24: =G23*'Cost Inputs'!$B$7*(1+'Cost Inputs'!$B$11)^(4) | H24: =H23*'Cost Inputs'!$B$7*(1+'Cost Inputs'!$B$11)^(5) | I24: =I23*'Cost Inputs'!$B$7*(1+'Cost Inputs'!$B$11)^(6) | J24: =J23*'Cost Inputs'!$B$7*(1+'Cost Inputs'!$B$11)^(7) | K24: =K23*'Cost Inputs'!$B$7*(1+'Cost Inputs'!$B$11)^(8) | L24: =L23*'Cost Inputs'!$B$7*(1+'Cost Inputs'!$B$11)^(9) | M24: =SUM(C24:L24)
A26: K8S AND QSERV PURCHASES
A27: K8s nodes purchased (growth + cohort refresh) | B27: nodes | C27: ='Cost Inputs'!$B$26 | D27: =ROUND('Key Numbers'!$B$65*'Cost Inputs'!$B$16,0)+IF(AND(COLUMN()+2026-3-'Cost Inputs'!$B$14>=2021,COLUMN()+2026-3-'Cost Inputs'!$B$14<=2025),INDEX('Cost Inputs'!$B$22:$F$22,1,COLUMN()+2026-3-'Cost Inputs'!$B$14-2020),0)+IF(COLUMN()-2>'Cost Inputs'!$B$14,INDEX($C$27:$L$27,1,COLUMN()-2-'Cost Inputs'!$B$14),0) | E27: =ROUND('Key Numbers'!$B$65*'Cost Inputs'!$B$16,0)+IF(AND(COLUMN()+2026-3-'Cost Inputs'!$B$14>=2021,COLUMN()+2026-3-'Cost Inputs'!$B$14<=2025),INDEX('Cost Inputs'!$B$22:$F$22,1,COLUMN()+2026-3-'Cost Inputs'!$B$14-2020),0)+IF(COLUMN()-2>'Cost Inputs'!$B$14,INDEX($C$27:$L$27,1,COLUMN()-2-'Cost Inputs'!$B$14),0) | F27: =ROUND('Key Numbers'!$B$65*'Cost Inputs'!$B$16,0)+IF(AND(COLUMN()+2026-3-'Cost Inputs'!$B$14>=2021,COLUMN()+2026-3-'Cost Inputs'!$B$14<=2025),INDEX('Cost Inputs'!$B$22:$F$22,1,COLUMN()+2026-3-'Cost Inputs'!$B$14-2020),0)+IF(COLUMN()-2>'Cost Inputs'!$B$14,INDEX($C$27:$L$27,1,COLUMN()-2-'Cost Inputs'!$B$14),0) | G27: =ROUND('Key Numbers'!$B$65*'Cost Inputs'!$B$16,0)+IF(AND(COLUMN()+2026-3-'Cost Inputs'!$B$14>=2021,COLUMN()+2026-3-'Cost Inputs'!$B$14<=2025),INDEX('Cost Inputs'!$B$22:$F$22,1,COLUMN()+2026-3-'Cost Inputs'!$B$14-2020),0)+IF(COLUMN()-2>'Cost Inputs'!$B$14,INDEX($C$27:$L$27,1,COLUMN()-2-'Cost Inputs'!$B$14),0) | H27: =ROUND('Key Numbers'!$B$65*'Cost Inputs'!$B$16,0)+IF(AND(COLUMN()+2026-3-'Cost Inputs'!$B$14>=2021,COLUMN()+2026-3-'Cost Inputs'!$B$14<=2025),INDEX('Cost Inputs'!$B$22:$F$22,1,COLUMN()+2026-3-'Cost Inputs'!$B$14-2020),0)+IF(COLUMN()-2>'Cost Inputs'!$B$14,INDEX($C$27:$L$27,1,COLUMN()-2-'Cost Inputs'!$B$14),0) | I27: =ROUND('Key Numbers'!$B$65*'Cost Inputs'!$B$16,0)+IF(AND(COLUMN()+2026-3-'Cost Inputs'!$B$14>=2021,COLUMN()+2026-3-'Cost Inputs'!$B$14<=2025),INDEX('Cost Inputs'!$B$22:$F$22,1,COLUMN()+2026-3-'Cost Inputs'!$B$14-2020),0)+IF(COLUMN()-2>'Cost Inputs'!$B$14,INDEX($C$27:$L$27,1,COLUMN()-2-'Cost Inputs'!$B$14),0) | J27: =ROUND('Key Numbers'!$B$65*'Cost Inputs'!$B$16,0)+IF(AND(COLUMN()+2026-3-'Cost Inputs'!$B$14>=2021,COLUMN()+2026-3-'Cost Inputs'!$B$14<=2025),INDEX('Cost Inputs'!$B$22:$F$22,1,COLUMN()+2026-3-'Cost Inputs'!$B$14-2020),0)+IF(COLUMN()-2>'Cost Inputs'!$B$14,INDEX($C$27:$L$27,1,COLUMN()-2-'Cost Inputs'!$B$14),0) | K27: =ROUND('Key Numbers'!$B$65*'Cost Inputs'!$B$16,0)+IF(AND(COLUMN()+2026-3-'Cost Inputs'!$B$14>=2021,COLUMN()+2026-3-'Cost Inputs'!$B$14<=2025),INDEX('Cost Inputs'!$B$22:$F$22,1,COLUMN()+2026-3-'Cost Inputs'!$B$14-2020),0)+IF(COLUMN()-2>'Cost Inputs'!$B$14,INDEX($C$27:$L$27,1,COLUMN()-2-'Cost Inputs'!$B$14),0) | L27: =ROUND('Key Numbers'!$B$65*'Cost Inputs'!$B$16,0)+IF(AND(COLUMN()+2026-3-'Cost Inputs'!$B$14>=2021,COLUMN()+2026-3-'Cost Inputs'!$B$14<=2025),INDEX('Cost Inputs'!$B$22:$F$22,1,COLUMN()+2026-3-'Cost Inputs'!$B$14-2020),0)+IF(COLUMN()-2>'Cost Inputs'!$B$14,INDEX($C$27:$L$27,1,COLUMN()-2-'Cost Inputs'!$B$14),0) | M27: =SUM(C27:L27)
A28: K8s cost | B28: $ | C28: ='Cost Inputs'!$B$27 | D28: =D27*'Cost Inputs'!$B$5*(1+'Cost Inputs'!$B$11)^(1) | E28: =E27*'Cost Inputs'!$B$5*(1+'Cost Inputs'!$B$11)^(2) | F28: =F27*'Cost Inputs'!$B$5*(1+'Cost Inputs'!$B$11)^(3) | G28: =G27*'Cost Inputs'!$B$5*(1+'Cost Inputs'!$B$11)^(4) | H28: =H27*'Cost Inputs'!$B$5*(1+'Cost Inputs'!$B$11)^(5) | I28: =I27*'Cost Inputs'!$B$5*(1+'Cost Inputs'!$B$11)^(6) | J28: =J27*'Cost Inputs'!$B$5*(1+'Cost Inputs'!$B$11)^(7) | K28: =K27*'Cost Inputs'!$B$5*(1+'Cost Inputs'!$B$11)^(8) | L28: =L27*'Cost Inputs'!$B$5*(1+'Cost Inputs'!$B$11)^(9) | M28: =SUM(C28:L28)
A29: Qserv nodes needed (from Qserv tab) | B29: nodes | C29: ='Qserv'!C39 | D29: ='Qserv'!D39 | E29: ='Qserv'!E39 | F29: ='Qserv'!F39 | G29: ='Qserv'!G39 | H29: ='Qserv'!H39 | I29: ='Qserv'!I39 | J29: ='Qserv'!J39 | ... L29: ='Qserv'!L39
A30: Running maximum needed | B30: nodes | C30: =MAX('Key Numbers'!$B$76,C29) | D30: =MAX(C30,D29) | E30: =MAX(D30,E29) | F30: =MAX(E30,F29) | G30: =MAX(F30,G29) | H30: =MAX(G30,H29) | I30: =MAX(H30,I29) | J30: =MAX(I30,J29) | K30: =MAX(J30,K29) | L30: =MAX(K30,L29)
A31: Qserv growth purchases | B31: nodes | C31: =MAX(0,C29-'Key Numbers'!$B$76) | D31: =D30-C30 | E31: =E30-D30 | F31: =F30-E30 | G31: =G30-F30 | H31: =H30-G30 | I31: =I30-H30 | J31: =J30-I30 | K31: =K30-J30 | L31: =L30-K30 | M31: =SUM(C31:L31)
A32: Qserv cohort refresh due this FY | B32: nodes | C32: =IF(AND(COLUMN()+2026-3-'Cost Inputs'!$B$14>=2021,COLUMN()+2026-3-'Cost Inputs'!$B$14<=2025),INDEX('Cost Inputs'!$B$21:$F$21,1,COLUMN()+2026-3-'Cost Inputs'!$B$14-2020),0)+IF(COLUMN()-2>'Cost Inputs'!$B$14,INDEX($C$33:$L$33,1,COLUMN()-2-'Cost Inputs'!$B$14),0) | D32: =IF(AND(COLUMN()+2026-3-'Cost Inputs'!$B$14>=2021,COLUMN()+2026-3-'Cost Inputs'!$B$14<=2025),INDEX('Cost Inputs'!$B$21:$F$21,1,COLUMN()+2026-3-'Cost Inputs'!$B$14-2020),0)+IF(COLUMN()-2>'Cost Inputs'!$B$14,INDEX($C$33:$L$33,1,COLUMN()-2-'Cost Inputs'!$B$14),0) | E32: =IF(AND(COLUMN()+2026-3-'Cost Inputs'!$B$14>=2021,COLUMN()+2026-3-'Cost Inputs'!$B$14<=2025),INDEX('Cost Inputs'!$B$21:$F$21,1,COLUMN()+2026-3-'Cost Inputs'!$B$14-2020),0)+IF(COLUMN()-2>'Cost Inputs'!$B$14,INDEX($C$33:$L$33,1,COLUMN()-2-'Cost Inputs'!$B$14),0) | F32: =IF(AND(COLUMN()+2026-3-'Cost Inputs'!$B$14>=2021,COLUMN()+2026-3-'Cost Inputs'!$B$14<=2025),INDEX('Cost Inputs'!$B$21:$F$21,1,COLUMN()+2026-3-'Cost Inputs'!$B$14-2020),0)+IF(COLUMN()-2>'Cost Inputs'!$B$14,INDEX($C$33:$L$33,1,COLUMN()-2-'Cost Inputs'!$B$14),0) | G32: =IF(AND(COLUMN()+2026-3-'Cost Inputs'!$B$14>=2021,COLUMN()+2026-3-'Cost Inputs'!$B$14<=2025),INDEX('Cost Inputs'!$B$21:$F$21,1,COLUMN()+2026-3-'Cost Inputs'!$B$14-2020),0)+IF(COLUMN()-2>'Cost Inputs'!$B$14,INDEX($C$33:$L$33,1,COLUMN()-2-'Cost Inputs'!$B$14),0) | H32: =IF(AND(COLUMN()+2026-3-'Cost Inputs'!$B$14>=2021,COLUMN()+2026-3-'Cost Inputs'!$B$14<=2025),INDEX('Cost Inputs'!$B$21:$F$21,1,COLUMN()+2026-3-'Cost Inputs'!$B$14-2020),0)+IF(COLUMN()-2>'Cost Inputs'!$B$14,INDEX($C$33:$L$33,1,COLUMN()-2-'Cost Inputs'!$B$14),0) | I32: =IF(AND(COLUMN()+2026-3-'Cost Inputs'!$B$14>=2021,COLUMN()+2026-3-'Cost Inputs'!$B$14<=2025),INDEX('Cost Inputs'!$B$21:$F$21,1,COLUMN()+2026-3-'Cost Inputs'!$B$14-2020),0)+IF(COLUMN()-2>'Cost Inputs'!$B$14,INDEX($C$33:$L$33,1,COLUMN()-2-'Cost Inputs'!$B$14),0) | J32: =IF(AND(COLUMN()+2026-3-'Cost Inputs'!$B$14>=2021,COLUMN()+2026-3-'Cost Inputs'!$B$14<=2025),INDEX('Cost Inputs'!$B$21:$F$21,1,COLUMN()+2026-3-'Cost Inputs'!$B$14-2020),0)+IF(COLUMN()-2>'Cost Inputs'!$B$14,INDEX($C$33:$L$33,1,COLUMN()-2-'Cost Inputs'!$B$14),0) | ... L32: =IF(AND(COLUMN()+2026-3-'Cost Inputs'!$B$14>=2021,COLUMN()+2026-3-'Cost Inputs'!$B$14<=2025),INDEX('Cost Inputs'!$B$21:$F$21,1,COLUMN()+2026-3-'Cost Inputs'!$B$14-2020),0)+IF(COLUMN()-2>'Cost Inputs'!$B$14,INDEX($C$33:$L$33,1,COLUMN()-2-'Cost Inputs'!$B$14),0) | M32: =SUM(C32:L32)
A33: Qserv nodes purchased | B33: nodes | C33: =C31+C32 | D33: =D31+D32 | E33: =E31+E32 | F33: =F31+F32 | G33: =G31+G32 | H33: =H31+H32 | I33: =I31+I32 | J33: =J31+J32 | ... L33: =L31+L32 | M33: =SUM(C33:L33)
A34: Qserv cost | B34: $ | C34: =C33*'Cost Inputs'!$B$5*(1+'Cost Inputs'!$B$11)^(0) | D34: =D33*'Cost Inputs'!$B$5*(1+'Cost Inputs'!$B$11)^(1) | E34: =E33*'Cost Inputs'!$B$5*(1+'Cost Inputs'!$B$11)^(2) | F34: =F33*'Cost Inputs'!$B$5*(1+'Cost Inputs'!$B$11)^(3) | G34: =G33*'Cost Inputs'!$B$5*(1+'Cost Inputs'!$B$11)^(4) | H34: =H33*'Cost Inputs'!$B$5*(1+'Cost Inputs'!$B$11)^(5) | I34: =I33*'Cost Inputs'!$B$5*(1+'Cost Inputs'!$B$11)^(6) | J34: =J33*'Cost Inputs'!$B$5*(1+'Cost Inputs'!$B$11)^(7) | K34: =K33*'Cost Inputs'!$B$5*(1+'Cost Inputs'!$B$11)^(8) | L34: =L33*'Cost Inputs'!$B$5*(1+'Cost Inputs'!$B$11)^(9) | M34: =SUM(C34:L34)
A36: HOSTING, OVERHEAD AND TOTALS
A37: Hardware subtotal | B37: $ | C37: =C15+C22+C24+C28+C34 | D37: =D15+D22+D24+D28+D34 | E37: =E15+E22+E24+E28+E34 | F37: =F15+F22+F24+F28+F34 | G37: =G15+G22+G24+G28+G34 | H37: =H15+H22+H24+H28+H34 | I37: =I15+I22+I24+I28+I34 | J37: =J15+J22+J24+J28+J34 | ... L37: =L15+L22+L24+L28+L34 | M37: =SUM(C37:L37)
A38: Nodes in service (approximate) | B38: nodes | C38: =335+SUM($C$12:C12)+SUM($C$31:C31)+SUM($C$27:C27) | D38: =335+SUM($C$12:D12)+SUM($C$31:D31)+SUM($C$27:D27) | E38: =335+SUM($C$12:E12)+SUM($C$31:E31)+SUM($C$27:E27) | F38: =335+SUM($C$12:F12)+SUM($C$31:F31)+SUM($C$27:F27) | G38: =335+SUM($C$12:G12)+SUM($C$31:G31)+SUM($C$27:G27) | H38: =335+SUM($C$12:H12)+SUM($C$31:H31)+SUM($C$27:H27) | I38: =335+SUM($C$12:I12)+SUM($C$31:I31)+SUM($C$27:I27) | J38: =335+SUM($C$12:J12)+SUM($C$31:J31)+SUM($C$27:J27) | ... L38: =335+SUM($C$12:L12)+SUM($C$31:L31)+SUM($C$27:L27)
A39: Hosting | B39: $ | C39: =C38*'Cost Inputs'!$B$8 | D39: =D38*'Cost Inputs'!$B$8 | E39: =E38*'Cost Inputs'!$B$8 | F39: =F38*'Cost Inputs'!$B$8 | G39: =G38*'Cost Inputs'!$B$8 | H39: =H38*'Cost Inputs'!$B$8 | I39: =I38*'Cost Inputs'!$B$8 | J39: =J38*'Cost Inputs'!$B$8 | ... L39: =L38*'Cost Inputs'!$B$8 | M39: =SUM(C39:L39)
A40: Overhead | B40: $ | C40: =C37*'Cost Inputs'!$B$9+'Cost Inputs'!$B$10 | D40: =D37*'Cost Inputs'!$B$9+'Cost Inputs'!$B$10 | E40: =E37*'Cost Inputs'!$B$9+'Cost Inputs'!$B$10 | F40: =F37*'Cost Inputs'!$B$9+'Cost Inputs'!$B$10 | G40: =G37*'Cost Inputs'!$B$9+'Cost Inputs'!$B$10 | H40: =H37*'Cost Inputs'!$B$9+'Cost Inputs'!$B$10 | I40: =I37*'Cost Inputs'!$B$9+'Cost Inputs'!$B$10 | J40: =J37*'Cost Inputs'!$B$9+'Cost Inputs'!$B$10 | ... L40: =L37*'Cost Inputs'!$B$9+'Cost Inputs'!$B$10 | M40: =SUM(C40:L40)
A41: TOTAL ANNUAL SPEND | B41: $ | C41: =C37+C39+C40 | D41: =D37+D39+D40 | E41: =E37+E39+E40 | F41: =F37+F39+F40 | G41: =G37+G39+G40 | H41: =H37+H39+H40 | I41: =I37+I39+I40 | J41: =J37+J39+J40 | ... L41: =L37+L39+L40 | M41: =SUM(C41:L41)
A42: TOTAL ANNUAL SPEND | B42: $M | C42: =C41 | D42: =D41 | E42: =E41 | F42: =F41 | G42: =G41 | H42: =H41 | I42: =I41 | J42: =J41 | ... L42: =L41 | M42: =SUM(C42:L42)
A43: Cumulative spend | B43: $M | C43: =C42 | D43: =C43+D42 | E43: =D43+E42 | F43: =E43+F42 | G43: =F43+G42 | H43: =G43+H42 | I43: =H43+I42 | J43: =I43+J42 | K43: =J43+K42 | L43: =K43+L42
A45: HOW THIS TAB WORKS — every row is a formula; the only tabs it reads are Key Numbers (sizing), Cost Inputs (costs), All at USDF (demand and disk need) and Qserv (node counts).
A46: Demand rows are linked straight from All at USDF so the two tabs can never disagree.
A47: Batch need: peak Milano-equivalent cores less the current fleet capacity, divided by the Milano-equivalent cores a new node contributes (cores/node x speedup). Growth takes the year-on-year increase, so a node is bought once and then kept.
A48: Cohort refresh: a purchase made in FY_x falls due in FY_x + compute lifetime. The first term looks up the historic grid on Cost Inputs; the second re-buys this tab's own earlier purchases. Changing the lifetime moves every replacement automatically.
A49: Disk: the need comes from All at USDF; purchases cover only the shortfall against what is already installed and previously bought, and capacity is re-bought once the storage lifetime expires.
A50: Tape: the increment in tape capacity that must be BOUGHT. Tape already on the floor and the capacity assumed available are netted off on All at USDF, so purchases begin only once the cumulative footprint exceeds that capacity.
A51: Qserv: node counts come from the Qserv tab. Purchases track the running maximum, so the cluster never shrinks, plus cohort refresh on the same rule as batch.
A52: Hosting scales with nodes in service; overhead is a percentage of the hardware subtotal plus a fixed annual amount.
A53: The first column uses the recorded actual requests from Cost Inputs rather than the model.
A54: SENSITIVITY: the live-intermediate fraction on Key Numbers is the single biggest driver of this forecast, and it is unmeasured. Change it there and every disk number moves.
